{"notes_translated":{"fr":"La 5e édition (1978 à 1995) de l’Atlas national du Canada contient une carte qui retrace l'exploration du Canada et des régions adjacentes des États-Unis et du Groenland. Les données illustrées sont les itinéraires des explorateurs, l'étendue du territoire connu des Européens et les zones de colonisation européenne. Un tableau donne des détails sur les voyages d'exploration et sur leurs raisons.","en":"Contained within the 5th Edition (1978 to 1995) of the National Atlas of Canada is a map that shows the extent of exploration during this period for Canada and adjacent areas of the United States and Greenland; data depicted are the routes of explorers, extent of territory known to Europeans, and settlement by Europeans. The table gives details on journeys of exploration and their motives."},"imso_approval":"true","maintainer":null,"association_type":[],"org_section":{},"jurisdiction":"federal","private":false,"maintainer_email":"NRCan.geogratis-geogratis.RNCan@canada.ca","num_tags":0,"contributor":{},"frequency":"as_needed","keywords":{"fr":["colonisation","histoire","recherche historique"],"en":["colonization","historical research","history"]},"data_series_issue_identification":{"fr":"mcr4138","en":"mcr4138"},"ready_to_publish":"true","id":"00ea8f26-0e33-582d-8408-4e061331b85a","metadata_created":"2016-09-24T00:07:26.670685","subject":["society_and_culture"],"spatial_representation_type":[],"metadata_modified":"2020-09-25T14:15:14.441518","author":null,"author_email":"NRCan.geogratis-geogratis.RNCan@canada.ca","geographic_region":[],"position_name":{},"portal_release_date":"2017-01-18","digital_object_identifier":"","state":"active","version":null,"presentation_form":"map_hardcopy","relationships_as_object":[],"creator_user_id":"aa584ab4-544c-4c5c-81da-d1cff9bd96fa","title_translated":{"fr":"L’exploration de 1651 à 1760","en":"Exploration 1651 - 1760"},"type":"dataset","resources":[{"cache_last_updated":null,"package_id":"00ea8f26-0e33-582d-8408-4e061331b85a","datastore_active":false,"id":"15a93726-9822-4666-96a4-09af30d38e51","size":3622881,"state":"active","name_translated":{"fr":"Télécharger le fichier en format anglais JPG via HTTP","en":"Download English JPG through HTTP"},"hash":"","description":"","format":"JPG","mimetype_inner":null,"url_type":null,"mimetype":null,"cache_url":null,"name":"Download English JPG through HTTP","language":["en","fr"],"created":"2017-01-26T11:21:50.437057","url":"http://ftp.geogratis.gc.ca/pub/nrcan_rncan/raster/atlas_5_ed/eng/historical/mcr4138.jpg","last_modified":null,"resource_type":"dataset","position":0,"revision_id":"0b14fb5a-c4b8-483d-947c-3680bac1fafb","data_quality":[]},{"cache_last_updated":null,"package_id":"00ea8f26-0e33-582d-8408-4e061331b85a","datastore_active":false,"id":"343a90cf-07bb-488d-b842-6a0b067499b7","size":3286447,"state":"active","name_translated":{"fr":"Télécharger le fichier en format anglais PDF via HTTP","en":"Download English PDF through HTTP"},"hash":"","description":"","format":"PDF","mimetype_inner":null,"url_type":null,"mimetype":null,"cache_url":null,"name":"Download English PDF through HTTP","language":["en","fr"],"created":"2017-01-26T11:21:50.437090","url":"http://ftp.geogratis.gc.ca/pub/nrcan_rncan/raster/atlas_5_ed/eng/historical/mcr4138.pdf","last_modified":null,"resource_type":"dataset","position":1,"revision_id":"af2c2f92-93c9-4ff9-a15c-d8a0146be625","data_quality":[]},{"cache_last_updated":null,"package_id":"00ea8f26-0e33-582d-8408-4e061331b85a","datastore_active":false,"id":"3d256a0c-9dfd-4db5-ad99-d98692eccfd6","size":4199606,"state":"active","name_translated":{"fr":"Télécharger le fichier en format francais JPG via HTTP","en":"Download French JPG through HTTP"},"hash":"","description":"","format":"JPG","mimetype_inner":null,"url_type":null,"mimetype":null,"cache_url":null,"name":"Download French JPG through HTTP","language":["en","fr"],"created":"2017-01-26T11:21:50.437104","url":"http://ftp.geogratis.gc.ca/pub/nrcan_rncan/raster/atlas_5_ed/fra/historical/mcr4138.jpg","last_modified":null,"resource_type":"dataset","position":2,"revision_id":"286e7c01-813a-4f18-b9df-630431378135","data_quality":[]},{"cache_last_updated":null,"package_id":"00ea8f26-0e33-582d-8408-4e061331b85a","datastore_active":false,"id":"8e849af9-63d9-4f35-97be-a03e5ddfff9f","size":3917085,"state":"active","name_translated":{"fr":"Télécharger le fichier en format francais PDF via HTTP","en":"Download French PDF through HTTP"},"hash":"","description":"","format":"PDF","mimetype_inner":null,"url_type":null,"mimetype":null,"cache_url":null,"name":"Download French PDF through HTTP","language":["en","fr"],"created":"2017-01-26T11:21:50.437117","url":"http://ftp.geogratis.gc.ca/pub/nrcan_rncan/raster/atlas_5_ed/fra/historical/mcr4138.pdf","last_modified":null,"resource_type":"dataset","position":3,"revision_id":"5486e3e9-b52a-4712-b79f-b79ac145b457","data_quality":[]}],"place_of_publication":[],"metadata_contact":{},"num_resources":4,"topic_category":["society"],"tags":[],"spatial":"{\"type\": \"Polygon\", \"coordinates\": [[[-175.0, 90.0], [-175.0, 40.0], [-30.0, 40.0], [-30.0, 90.0], [-175.0, 90.0]]]}","collection":"geogratis","org_title_at_publication":{"fr":"Ressources naturelles Canada","en":"Natural Resources Canada"},"date_published":"1991-02-16 00:00:00","display_flags":[],"groups":[],"license_id":"ca-ogl-lgo","data_series_name":{"fr":"Atlas du Canada, 5e édition","en":"Atlas of Canada, 5th Edition"},"relationships_as_subject":[],"license_title":"Open Government Licence - Canada","restrictions":"unrestricted","organization":{"description":"","created":"2016-09-23T17:25:46.737130","title":"Natural Resources Canada | Ressources naturelles Canada","name":"nrcan-rncan","is_organization":true,"state":"active","image_url":"","revision_id":"a0c5bf0d-8541-443d-a8bf-b04a249733f4","type":"organization","id":"9391E0A2-9717-4755-B548-4499C21F917B","approval_status":"approved"},"name":"00ea8f26-0e33-582d-8408-4e061331b85a","isopen":false,"url":"{u'fr': u'http://geogratis.gc.ca/api/fr/nrcan-rncan/ess-sst/00ea8f26-0e33-582d-8408-4e061331b85a', u'en': u'http://geogratis.gc.ca/api/en/nrcan-rncan/ess-sst/00ea8f26-0e33-582d-8408-4e061331b85a'}","notes":"Contained within the 5th Edition (1978 to 1995) of the National Atlas of Canada is a map that shows the extent of exploration during this period for Canada and adjacent areas of the United States and Greenland; data depicted are the routes of explorers, extent of territory known to Europeans, and settlement by Europeans. The table gives details on journeys of exploration and their motives.","owner_org":"9391E0A2-9717-4755-B548-4499C21F917B","audience":[],"license_url":"http://open.canada.ca/en/open-government-licence-canada","program_page_url":{},"title":"Exploration 1651 - 1760","revision_id":"bde147f9-efe7-43bc-bf3b-9c975a0afb06"}