{"issuance_frequency":"","notes_translated":{"fr":"Les vaccins sont le moyen le plus efficace de prévenir la propagation des maladies infectieuses, mais en développer un peut être coûteux, long et complexe. Un vaccin sécuritaire et efficace contre la COVID-19 nous rapprochera de la gestion généralisée et à long terme de cette pandémie.","en":"Vaccines are the most effective way to prevent the spread of infectious disease, but developing one can be costly, long, and complex. A safe and effective vaccine will bring us one step closer to the widespread and long-term management of COVID-19."},"issn":"","imso_approval":"true","isbn":"","creator":"","org_section":{"fr":"","en":""},"jurisdiction":"federal","private":false,"maintainer_email":"open-ouvert@tbs-sct.gc.ca","num_tags":0,"edition":"","frequency":"unknown","data_series_issue_identification":{"fr":"","en":""},"contributor":{"fr":"","en":""},"maintainer":null,"ready_to_publish":"true","id":"016a89d5-f91e-4ea6-a8bc-192105d102c4","metadata_created":"2021-01-29T17:21:02.943262","subject":["health_and_safety"],"date_modified":"2020-12-21 00:00:00","pspc_identification_number":"","metadata_modified":"2021-01-29T17:21:02.943267","author":null,"author_email":null,"geographic_region":[],"portal_release_date":"2021-01-29","digital_object_identifier":"","state":"active","version":null,"keywords":{"fr":["COVID-19","Coronavrius","vidéo","vaccin","une seringue","exploratoire","préclinique","clinique","la recherche","le virus"],"en":["COVID-19","Coronavirus","video","vaccine","syringe","exploratory","pre-clinical","clinical","research","virus"]},"relationships_as_object":[],"creator_user_id":"2dc5a12f-2a6f-4822-8514-165ea6bb05d9","title_translated":{"fr":"COVID-19 : Comment les vaccins sont créés","en":"COVID-19: How vaccines are developed "},"type":"info","resources":[{"cache_last_updated":null,"unique_identifier":"","package_id":"016a89d5-f91e-4ea6-a8bc-192105d102c4","datastore_active":false,"character_set":"","related_type":"","state":"active","id":"acd4abb3-797c-4bed-b48a-5891a7451b83","related_relationship":"","name_translated":{"fr":"COVID-19 : Comment les vaccins sont créés","en":"COVID-19: How vaccines are developed "},"hash":"","description":"","format":"HTML","date_published":"","mimetype_inner":null,"url_type":null,"mimetype":null,"cache_url":null,"name":"COVID-19: How vaccines are developed ","language":["en"],"created":"2021-01-29T17:21:03.056846","url":"https://www.canada.ca/en/public-health/services/video/covid-19-how-vaccines-developed.html","last_modified":null,"position":0,"revision_id":"6acb602b-ca09-47fd-8cca-7e7d57710cf7","resource_type":"website"},{"cache_last_updated":null,"unique_identifier":"","package_id":"016a89d5-f91e-4ea6-a8bc-192105d102c4","datastore_active":false,"character_set":"","related_type":"","state":"active","id":"ecf38709-35d4-4ae1-b8b6-a54b178ced5c","related_relationship":"","name_translated":{"fr":"COVID-19 : Comment les vaccins sont créés","en":"COVID-19: How vaccines are developed "},"hash":"","description":"","format":"HTML","date_published":"","mimetype_inner":null,"url_type":null,"mimetype":null,"cache_url":null,"name":"COVID-19: How vaccines are developed ","language":["fr"],"created":"2021-01-29T17:21:03.056852","url":"https://www.canada.ca/fr/sante-publique/services/video/covid-19-comment-vaccins-crees.html","last_modified":null,"position":1,"revision_id":"6acb602b-ca09-47fd-8cca-7e7d57710cf7","resource_type":"website"},{"cache_last_updated":null,"unique_identifier":"","package_id":"016a89d5-f91e-4ea6-a8bc-192105d102c4","datastore_active":false,"character_set":"","related_type":"","state":"active","id":"200d438a-3f85-4dd2-ac01-fec8f9faec6a","related_relationship":"","name_translated":{"fr":"COVID-19 : Comment les vaccins sont créés (vidéo description)","en":"COVID-19: How vaccines are developed (described video)"},"hash":"","description":"","format":"HTML","date_published":"","mimetype_inner":null,"url_type":null,"mimetype":null,"cache_url":null,"name":"COVID-19: How vaccines are developed (described video)","language":["en"],"created":"2021-01-29T17:21:03.056854","url":"https://www.canada.ca/en/public-health/services/video/covid-19-how-vaccines-developed-described-video.html","last_modified":null,"position":2,"revision_id":"6acb602b-ca09-47fd-8cca-7e7d57710cf7","resource_type":"website"},{"cache_last_updated":null,"unique_identifier":"","package_id":"016a89d5-f91e-4ea6-a8bc-192105d102c4","datastore_active":false,"character_set":"","related_type":"","state":"active","id":"3a8a5000-b1aa-4d06-854e-81cf2e929e2a","related_relationship":"","name_translated":{"fr":"COVID-19 : Comment les vaccins sont créés (vidéo description)","en":"COVID-19: How vaccines are developed (described video)"},"hash":"","description":"","format":"HTML","date_published":"","mimetype_inner":null,"url_type":null,"mimetype":null,"cache_url":null,"name":"COVID-19: How vaccines are developed (described video)","language":["fr"],"created":"2021-01-29T17:21:03.056857","url":"https://www.canada.ca/fr/sante-publique/services/video/covid-19-comment-vaccins-crees-video-description.html","last_modified":null,"position":3,"revision_id":"6acb602b-ca09-47fd-8cca-7e7d57710cf7","resource_type":"website"}],"place_of_publication":[],"num_resources":4,"tags":[],"spatial":"","collection":"publication","org_title_at_publication":{"fr":"Agence de la santé publique du Canada","en":"Public Health Agency of Canada"},"date_published":"2020-12-08 00:00:00","issuance":"","groups":[],"license_id":"ca-ogl-lgo","data_series_name":{"fr":"","en":""},"relationships_as_subject":[],"license_title":"Open Government Licence - Canada","restrictions":"unrestricted","organization":{"description":"","created":"2016-09-23T17:25:57.068700","title":"Public Health Agency of Canada | Agence de la santé publique du Canada","name":"phac-aspc","is_organization":true,"state":"active","image_url":"","revision_id":"96161da6-edc7-4d1d-99e0-baac9df7b3b9","type":"organization","id":"1C71053B-AA64-4646-956B-41631C396018","approval_status":"approved"},"name":"016a89d5-f91e-4ea6-a8bc-192105d102c4","isopen":false,"additional_notes":{"fr":"","en":""},"departmental_identification_number":"","notes":"Vaccines are the most effective way to prevent the spread of infectious disease, but developing one can be costly, long, and complex. A safe and effective vaccine will bring us one step closer to the widespread and long-term management of COVID-19.","owner_org":"1C71053B-AA64-4646-956B-41631C396018","program_page_url":{"fr":"","en":""},"url":null,"audience":[],"gc_catalogue_number":"","license_url":"http://open.canada.ca/en/open-government-licence-canada","series_publication_dates":{"fr":"","en":""},"title":"COVID-19: How vaccines are developed ","revision_id":"6acb602b-ca09-47fd-8cca-7e7d57710cf7"}