{"notes_translated":{"fr-t-en":"Polygones représentant les limites des circonscriptions électorales municipales régionales.","en":"Polygons representing the limits of each municipal regional electoral district."},"place_of_publication":[],"imso_approval":"true","maintainer":null,"creator":"","association_type":[],"org_section":{},"jurisdiction":"provincial","private":false,"maintainer_email":"opendatadonneesouvertes@snb.ca","num_tags":0,"contributor":{},"frequency":"unknown","distributor":"{\"fr\": {\"pays\": \"\", \"adresse\": \"\", \"telephone\": \"\", \"nom_organization\": \"Gouvernement du Nouveau-Brunswick; Gouvernement du Nouveau-Brunswick; \\u00c9lections Nouveau-Brunswick\", \"zone_administrative\": \"\", \"electronic_mail_address\": \"opendatadonneesouvertes@snb.ca\"}, \"en\": {\"administrative_area\": \"\", \"city\": \"\", \"country\": \"\", \"organization_name\": \"Government of New Brunswick; Government of New Brunswick; Elections New Brunswick\", \"phone\": \"\", \"postal_code\": \"\", \"address\": \"\", \"electronic_mail_address\": \"opendatadonneesouvertes@snb.ca\"}}","data_series_issue_identification":{},"ready_to_publish":"true","id":"05cb4986-d4f3-f13d-2758-2df903b1fbb8","metadata_created":"2021-04-20T15:04:06.905518","subject":["government_and_politics"],"hierarchy_level":"dataset; jeuDonnées","spatial_representation_type":["vector"],"metadata_modified":"2021-05-06T13:54:04.993177","author":null,"author_email":null,"geographic_region":[],"position_name":{"fr":"","en":""},"keywords":{"fr-t-en":["carte","géonb","gouvernement local","élections","votant","vote","gouvernements locaux","Information gouvernementale"],"en":["map","geonb","local government","elections","voting","vote","local governments","Government information"]},"contact_information":"{\"fr\": {\"pays\": \"\", \"point_de_livraison\": \"\", \"zone_administrative\": \"\", \"electronic_mail_address\": \"opendatadonneesouvertes@snb.ca\"}, \"en\": {\"city\": \"\", \"administrative_area\": \"\", \"country\": \"\", \"postal_code\": \"\", \"delivery_point\": \"\", \"electronic_mail_address\": \"opendatadonneesouvertes@snb.ca\"}}","state":"active","version":null,"relationships_as_object":[],"time_period_coverage_start":"0001-01-01 00:00:00","title_translated":{"fr-t-en":"Circonscriptions électorales régionales municipales","en":"Municipal Regional Electoral Districts"},"type":"dataset","resources":[{"cache_last_updated":null,"package_id":"05cb4986-d4f3-f13d-2758-2df903b1fbb8","datastore_active":false,"id":"3da4c007-069c-4fee-885e-7a79173a3ab2","state":"active","name_translated":{"fr-t-en":"Métadonnées originales du Nouveau-Brunswick (https://gnb.socrata.com)","en":"New Brunswick original metadata (https://gnb.socrata.com)"},"hash":"","description":"","format":"HTML","mimetype_inner":null,"url_type":null,"mimetype":null,"cache_url":null,"name":"New Brunswick original metadata (https://gnb.socrata.com)","language":["en"],"created":"2021-05-06T13:54:05.040032","url":"https://gnb.socrata.com/datasets/u755-jbxe","last_modified":null,"data_quality":[],"position":0,"revision_id":"b1a499ae-36de-4d05-87d2-104082a512d4","resource_type":"dataset"},{"cache_last_updated":null,"package_id":"05cb4986-d4f3-f13d-2758-2df903b1fbb8","datastore_active":false,"id":"f476913d-aa22-496e-aa6e-5171aa66c8ee","state":"active","name_translated":{"fr-t-en":"FGDB","en":"FGDB"},"hash":"","description":"","format":"ZIP","mimetype_inner":null,"url_type":null,"mimetype":null,"cache_url":null,"name":"FGDB","language":["en"],"created":"2021-05-06T13:54:05.040039","url":"http://geonb.snb.ca/downloads/mun_electoral_districts/geonb_mred-cerm_fgdb.zip","last_modified":null,"data_quality":[],"position":1,"revision_id":"b1a499ae-36de-4d05-87d2-104082a512d4","resource_type":"dataset"},{"cache_last_updated":null,"package_id":"05cb4986-d4f3-f13d-2758-2df903b1fbb8","datastore_active":false,"id":"385a482b-26c3-4a37-9c17-519b5cdf72aa","state":"active","name_translated":{"fr-t-en":"SHP","en":"SHP"},"hash":"","description":"","format":"ZIP","mimetype_inner":null,"url_type":null,"mimetype":null,"cache_url":null,"name":"SHP","language":["en"],"created":"2021-05-06T13:54:05.040042","url":"http://geonb.snb.ca/downloads/mun_electoral_districts/geonb_mred-cerm_shp.zip","last_modified":null,"data_quality":[],"position":2,"revision_id":"b1a499ae-36de-4d05-87d2-104082a512d4","resource_type":"dataset"}],"status":"ongoing","metadata_contact":{"fr":"Gouvernement du Nouveau-Brunswick; Gouvernement du Nouveau-Brunswick; Élections Nouveau-Brunswick,opendatadonneesouvertes@snb.ca","en":"Government of New Brunswick; Government of New Brunswick; Elections New Brunswick,,opendatadonneesouvertes@snb.ca"},"num_resources":3,"topic_category":["boundaries"],"tags":[],"aggregate_identifier":"","responsible_role":"RI_414","spatial":"{\"type\": \"Polygon\", \"coordinates\": [[[-69.0534663, 44.299667], [-63.328871, 44.299667], [-63.328871, 48.2206848], [-69.0534663, 48.2206848], [-69.0534663, 44.299667]]]}","collection":"fgp","org_title_at_publication":{"fr":"Gouvernement du Nouveau-Brunswick","en":"Government of New Brunswick"},"date_published":"2019-08-24 00:00:00","display_flags":[],"reference_system_information":"unknown,unknown,unknown","groups":[],"creator_user_id":"b88b9549-3a4b-43a9-9375-5f3fc20fe782","data_series_name":{},"relationships_as_subject":[],"license_title":"Open Government Licence - New Brunswick","restrictions":"unrestricted","organization":{"description":"","created":"2020-05-14T14:46:30.600688","title":"Government of New Brunswick | Gouvernement du Nouveau-Brunswick","name":"nb","is_organization":true,"state":"active","image_url":"","revision_id":"8737e51b-b0ca-4779-9216-19f246571cec","type":"organization","id":"15f95d08-fb23-48d4-876e-2f29e1916b55","approval_status":"approved"},"name":"05cb4986-d4f3-f13d-2758-2df903b1fbb8","isopen":false,"license_id":"nb-oglnb","url":null,"notes":"Polygons representing the limits of each municipal regional electoral district.","owner_org":"15f95d08-fb23-48d4-876e-2f29e1916b55","audience":[],"license_url":"http://www.snb.ca/e/2000/data-E.html","program_page_url":{},"title":"Municipal Regional Electoral Districts","revision_id":"6a4a97be-a16a-4ac8-8371-3ab4950303db","file_id":"05cb4986-d4f3-f13d-2758-2df903b1fbb8"}