{"issuance_frequency":"","notes_translated":{"fr":"Déraillement de train en voie principale, Chemin de fer Canadien Pacifique, Train de marchandises 142-14, Point milliaire 36,6, subdivision de Winchester, Saint-Polycarpe (Québec),16 juillet 2018","en":"Main-track train derailment, Canadian Pacific Railway, ,freight train 142-14, Mile 36.6, Winchester Subdivision, Saint-Polycarpe, Quebec, 16 July 2018 "},"issn":"","imso_approval":"true","isbn":"","creator":"","org_section":{"fr":"","en":""},"jurisdiction":"federal","private":false,"maintainer_email":"open-ouvert@tbs-sct.gc.ca","num_tags":0,"edition":"","frequency":"not_planned","data_series_issue_identification":{"fr":"","en":""},"contributor":{"fr":"","en":""},"maintainer":null,"ready_to_publish":"true","id":"1188d0f0-099b-4c3e-8d8f-9432336a84ed","metadata_created":"2019-12-11T15:42:05.623840","subject":["transport"],"pspc_identification_number":"","metadata_modified":"2019-12-11T15:42:05.623848","author":null,"author_email":null,"geographic_region":[],"portal_release_date":"2019-12-11","digital_object_identifier":"","state":"active","version":null,"keywords":{"fr":["rapport d'enquête de sécurité"],"en":["safety investigation report"]},"relationships_as_object":[],"creator_user_id":"4cfa9a9c-1d95-40eb-86f9-bc0c8ec45d1f","title_translated":{"fr":"Rapport d’enquête sur la sécurité du transport ferroviaire R18D0069","en":"Rail transportation safety investigation report R18D0069"},"type":"info","resources":[{"cache_last_updated":null,"unique_identifier":"","package_id":"1188d0f0-099b-4c3e-8d8f-9432336a84ed","datastore_active":false,"character_set":"","related_type":"","state":"active","id":"b3f896c4-eb30-4737-97d2-a552c55f1f99","related_relationship":"","name_translated":{"fr":"Rapport d'enquête R18D0069","en":"Investigation report R18D0069"},"hash":"","description":"","format":"HTML","date_published":"","mimetype_inner":null,"url_type":null,"mimetype":null,"cache_url":null,"name":"Investigation report R18D0069","language":["en"],"created":"2019-12-11T15:42:08.853070","url":"http://www.bst-tsb.gc.ca/eng/rapports-reports/rail/2018/r18d0069/r18d0069.html","last_modified":null,"position":0,"revision_id":"1a800e50-9ef2-421a-9ed2-887e16b0362b","resource_type":"report"},{"cache_last_updated":null,"unique_identifier":"","package_id":"1188d0f0-099b-4c3e-8d8f-9432336a84ed","datastore_active":false,"character_set":"","related_type":"","state":"active","id":"739bbe9c-b408-4235-b432-8cea808aa3f6","related_relationship":"","name_translated":{"fr":"Rapport d'enquête R18D0069","en":"Investigation report R18D0069"},"hash":"","description":"","format":"HTML","date_published":"","mimetype_inner":null,"url_type":null,"mimetype":null,"cache_url":null,"name":"Investigation report R18D0069","language":["fr"],"created":"2019-12-11T15:42:08.853077","url":"http://www.bst-tsb.gc.ca/fra/rapports-reports/rail/2018/r18d0069/r18d0069.html","last_modified":null,"position":1,"revision_id":"1a800e50-9ef2-421a-9ed2-887e16b0362b","resource_type":"report"},{"cache_last_updated":null,"unique_identifier":"","package_id":"1188d0f0-099b-4c3e-8d8f-9432336a84ed","datastore_active":false,"character_set":"","related_type":"","state":"active","id":"0015888a-fac4-4bc6-b7e0-3e96fe3e5f5e","related_relationship":"","name_translated":{"fr":"Rapport d'enquête R18D0069","en":"Investigation report R18D0069"},"hash":"","description":"","format":"PDF","date_published":"","mimetype_inner":null,"url_type":"upload","mimetype":null,"cache_url":null,"name":"Investigation report R18D0069","language":["en"],"created":"2019-12-11T15:42:08.853080","url":"https://open.canada.ca/data/dataset/1188d0f0-099b-4c3e-8d8f-9432336a84ed/resource/0015888a-fac4-4bc6-b7e0-3e96fe3e5f5e/download/r18d0069.pdf","last_modified":null,"position":2,"revision_id":"1a800e50-9ef2-421a-9ed2-887e16b0362b","resource_type":"report"},{"cache_last_updated":null,"unique_identifier":"","package_id":"1188d0f0-099b-4c3e-8d8f-9432336a84ed","datastore_active":false,"character_set":"","related_type":"","state":"active","id":"8e1765ae-1986-4eb7-828b-839fa035b012","related_relationship":"","name_translated":{"fr":"Rapport d'enquête R18D0069","en":"Investigation report R18D0069"},"hash":"","description":"","format":"PDF","date_published":"","mimetype_inner":null,"url_type":"upload","mimetype":null,"cache_url":null,"name":"Investigation report R18D0069","language":["fr"],"created":"2019-12-11T15:42:08.853082","url":"https://open.canada.ca/data/dataset/1188d0f0-099b-4c3e-8d8f-9432336a84ed/resource/8e1765ae-1986-4eb7-828b-839fa035b012/download/r18d0069f.pdf","last_modified":null,"position":3,"revision_id":"1a800e50-9ef2-421a-9ed2-887e16b0362b","resource_type":"report"}],"place_of_publication":[],"num_resources":4,"tags":[],"spatial":"","collection":"publication","org_title_at_publication":{"fr":"Bureau de la sécurité des transports du Canada","en":"Transportation Safety Board of Canada"},"date_published":"2019-12-09 00:00:00","issuance":"","groups":[],"license_id":"ca-ogl-lgo","data_series_name":{"fr":"","en":""},"relationships_as_subject":[],"license_title":"Open Government Licence - Canada","restrictions":"unrestricted","organization":{"description":"","created":"2016-09-23T17:26:19.010208","title":"Transportation Safety Board of Canada | Bureau de la sécurité des transports du Canada","name":"tsb-bst","is_organization":true,"state":"active","image_url":"","revision_id":"ebe3251f-c229-4292-881e-446a51c93cd4","type":"organization","id":"6D84AB23-F352-42EF-9F6E-F025F17F9675","approval_status":"approved"},"name":"1188d0f0-099b-4c3e-8d8f-9432336a84ed","isopen":false,"additional_notes":{"fr":"","en":""},"departmental_identification_number":"","notes":"Main-track train derailment, Canadian Pacific Railway, ,freight train 142-14, Mile 36.6, Winchester Subdivision, Saint-Polycarpe, Quebec, 16 July 2018 ","owner_org":"6D84AB23-F352-42EF-9F6E-F025F17F9675","program_page_url":{"fr":"","en":""},"url":null,"audience":[],"gc_catalogue_number":"","license_url":"http://open.canada.ca/en/open-government-licence-canada","series_publication_dates":{"fr":"","en":""},"title":"Rail transportation safety investigation report R18D0069","revision_id":"1a800e50-9ef2-421a-9ed2-887e16b0362b"}