{"notes_translated":{"fr":"Ce tableau statistique illustre le nombre de pensions devenues payables aux hommes et aux femmes (par année civile), le montant total en dollars des pensions versées et le montant moyen de la pension. Tous les montants comprennent l’indexation.","en":"This statistical table illustrates the number of pensions that became payable to men and women (per calendar year), the total dollar amount of pensions paid and the average pension amount. All amounts include indexation."},"imso_approval":"true","maintainer":null,"association_type":[],"org_section":{},"jurisdiction":"federal","private":false,"maintainer_email":"open-ouvert@tbs-sct.gc.ca","num_tags":0,"contributor":{},"frequency":"P1Y","keywords":{"fr":["régime de retraite de la fonction publique","montant total payé","pension moyenne"],"en":["public service pension plan","total amount paid","average pension"]},"data_series_issue_identification":{"fr":"","en":""},"ready_to_publish":"true","id":"33ee0fd0-2796-4f9d-aba7-50c351a56122","metadata_created":"2016-09-24T08:17:07.248287","subject":["economics_and_industry","government_and_politics","society_and_culture"],"spatial_representation_type":[],"metadata_modified":"2017-02-10T19:20:57.786730","author":null,"author_email":"open-ouvert@tbs-sct.gc.ca","geographic_region":[],"position_name":{},"portal_release_date":"2016-02-26","digital_object_identifier":"","state":"active","version":null,"presentation_form":"","relationships_as_object":[],"creator_user_id":"aa584ab4-544c-4c5c-81da-d1cff9bd96fa","title_translated":{"fr":"Rapport sur le régime de retraite de la fonction publique – Tableau statistique 2.1.","en":"Report on the Public Service Pension Plan – Statistical Table 2.1."},"type":"dataset","resources":[{"resource_group_id":"9518060e-a963-431f-b87c-33de830cb186","cache_last_updated":null,"package_id":"33ee0fd0-2796-4f9d-aba7-50c351a56122","datastore_active":false,"id":"29298eb7-dfbf-4166-93ca-6e737a7bda36","state":"active","name_translated":{"fr":"Tableau statistique 2.1. Pensions devenues payables","en":"Statistical Table 2.1. Pensions That Became Payable"},"hash":"","description":"","format":"XML","mimetype_inner":null,"url_type":null,"mimetype":null,"cache_url":null,"name":"Statistical Table 2.1. Pensions That Became Payable","language":["en"],"created":"2016-12-01T12:53:08.493167","url":"http://www.tbs-sct.gc.ca/data-donnees/pensions/service/Service2.svc/p21XMLEn/2014","last_modified":null,"resource_type":"dataset","position":0,"revision_id":"02b7350f-f9c5-424c-96e8-79a5afe21c33","data_quality":[]},{"resource_group_id":"9518060e-a963-431f-b87c-33de830cb186","cache_last_updated":null,"package_id":"33ee0fd0-2796-4f9d-aba7-50c351a56122","datastore_active":false,"id":"24bb5342-9548-43e4-b34d-244c1ecae5e0","state":"active","name_translated":{"fr":"Tableau statistique 2.1. Pensions devenues payables","en":"Statistical Table 2.1. Pensions That Became Payable"},"hash":"","description":"","format":"XML","mimetype_inner":null,"url_type":null,"mimetype":null,"cache_url":null,"name":"Statistical Table 2.1. Pensions That Became Payable","language":["fr"],"created":"2016-12-01T12:53:08.493242","url":"http://www.tbs-sct.gc.ca/data-donnees/pensions/service/Service2.svc/p21XMLFr/2014","last_modified":null,"resource_type":"dataset","position":1,"revision_id":"02b7350f-f9c5-424c-96e8-79a5afe21c33","data_quality":[]},{"resource_group_id":"9518060e-a963-431f-b87c-33de830cb186","cache_last_updated":null,"package_id":"33ee0fd0-2796-4f9d-aba7-50c351a56122","datastore_active":false,"id":"85897820-8505-441f-a86f-f3d6b5883877","state":"active","name_translated":{"fr":"Tableau statistique 2.1. Pensions devenues payables","en":"Statistical Table 2.1. Pensions That Became Payable"},"hash":"","description":"","format":"CSV","mimetype_inner":null,"url_type":null,"mimetype":null,"cache_url":null,"name":"Statistical Table 2.1. Pensions That Became Payable","language":["en"],"created":"2016-12-01T12:53:08.493281","url":"http://www.tbs-sct.gc.ca/data-donnees/pensions/csv/pensionsPayablepensionsPayables-en.csv","last_modified":null,"resource_type":"dataset","position":2,"revision_id":"02b7350f-f9c5-424c-96e8-79a5afe21c33","data_quality":[]},{"resource_group_id":"9518060e-a963-431f-b87c-33de830cb186","cache_last_updated":null,"package_id":"33ee0fd0-2796-4f9d-aba7-50c351a56122","datastore_active":false,"id":"7ef44786-ed3c-4dce-9946-35c376e6f751","state":"active","name_translated":{"fr":"Tableau statistique 2.1. Pensions devenues payables","en":"Statistical Table 2.1. Pensions That Became Payable"},"hash":"","description":"","format":"CSV","mimetype_inner":null,"url_type":null,"mimetype":null,"cache_url":null,"name":"Statistical Table 2.1. Pensions That Became Payable","language":["fr"],"created":"2016-12-01T12:53:08.493313","url":"http://www.tbs-sct.gc.ca/data-donnees/pensions/csv/pensionsPayablepensionsPayables-fr.csv","last_modified":null,"resource_type":"dataset","position":3,"revision_id":"02b7350f-f9c5-424c-96e8-79a5afe21c33","data_quality":[]},{"resource_group_id":"9518060e-a963-431f-b87c-33de830cb186","cache_last_updated":null,"package_id":"33ee0fd0-2796-4f9d-aba7-50c351a56122","datastore_active":false,"id":"1e63b17d-4c2d-4270-97f2-29d1d795d003","state":"active","name_translated":{"fr":"Tableau statistique 2.1. Pensions devenues payables","en":"Statistical Table 2.1. Pensions That Became Payable"},"hash":"","description":"","format":"TXT","mimetype_inner":null,"url_type":null,"mimetype":null,"cache_url":null,"name":"Statistical Table 2.1. Pensions That Became Payable","language":["en"],"created":"2016-12-01T12:53:08.493342","url":"http://www.tbs-sct.gc.ca/data-donnees/pensions/service/Service2.svc/p21TXT/21/1","last_modified":null,"resource_type":"dataset","position":4,"revision_id":"02b7350f-f9c5-424c-96e8-79a5afe21c33","data_quality":[]},{"resource_group_id":"9518060e-a963-431f-b87c-33de830cb186","cache_last_updated":null,"package_id":"33ee0fd0-2796-4f9d-aba7-50c351a56122","datastore_active":false,"id":"f4d90214-b2fe-4308-a7ba-1bbf66a27679","state":"active","name_translated":{"fr":"Tableau statistique 2.1. Pensions devenues payables","en":"Statistical Table 2.1. Pensions That Became Payable"},"hash":"","description":"","format":"TXT","mimetype_inner":null,"url_type":null,"mimetype":null,"cache_url":null,"name":"Statistical Table 2.1. Pensions That Became Payable","language":["fr"],"created":"2016-12-01T12:53:08.493371","url":"http://www.tbs-sct.gc.ca/data-donnees/pensions/service/Service2.svc/p21TXT/21/2","last_modified":null,"resource_type":"dataset","position":5,"revision_id":"02b7350f-f9c5-424c-96e8-79a5afe21c33","data_quality":[]},{"cache_last_updated":null,"unique_identifier":"","package_id":"33ee0fd0-2796-4f9d-aba7-50c351a56122","datastore_active":false,"character_set":"","related_type":"","state":"active","id":"13c29f60-9ebf-41e3-b014-48a23628502e","related_relationship":"","name_translated":{"fr":"Rapport sur le régime de retraite de la fonction publique pour l'exercice terminé le 31 mars 2015","en":"Report on the Public Service Pension Plan for the Fiscal Year Ended March 31, 2015"},"hash":"","description":"","format":"HTML","date_published":"","mimetype_inner":null,"url_type":"","mimetype":null,"cache_url":null,"name":"Report on the Public Service Pension Plan for the Fiscal Year Ended March 31, 2015","language":["en"],"created":"2016-12-15T14:20:19.109112","url":"https://www.canada.ca/en/treasury-board-secretariat/services/pension-plan/pension-publications/reports/pension-plan-report/fiscal-year-ended-march-31-2015.html","last_modified":null,"resource_type":"website","position":6,"revision_id":"03c13216-386c-4ce5-991d-2b6b8fd5b347","data_quality":[]},{"cache_last_updated":null,"unique_identifier":"","package_id":"33ee0fd0-2796-4f9d-aba7-50c351a56122","datastore_active":false,"character_set":"","related_type":"","state":"active","id":"4ace400d-2fff-4a11-a21c-859d25c907bb","related_relationship":"","name_translated":{"fr":"Rapport sur le régime de retraite de la fonction publique pour l'exercice terminé le 31 mars 2015","en":"Report on the Public Service Pension Plan for the Fiscal Year Ended March 31, 2015"},"hash":"","description":"","format":"HTML","date_published":"","mimetype_inner":null,"url_type":"","mimetype":null,"cache_url":null,"name":"Report on the Public Service Pension Plan for the Fiscal Year Ended March 31, 2015","language":["fr"],"created":"2016-12-15T14:20:19.109163","url":"https://www.canada.ca/fr/secretariat-conseil-tresor/services/regime-retraite/pension-publications/rapports/rapport-regime-retraite/exercice-termine-31-mars-2015.html","last_modified":null,"resource_type":"website","position":7,"revision_id":"03c13216-386c-4ce5-991d-2b6b8fd5b347","data_quality":[]}],"place_of_publication":[],"metadata_contact":{},"num_resources":8,"topic_category":["economy","society"],"tags":[],"spatial":"","collection":"primary","org_title_at_publication":{"fr":"Secrétariat du Conseil du Trésor du Canada","en":"Treasury Board of Canada Secretariat"},"date_published":"2016-02-26 00:00:00","display_flags":[],"groups":[],"license_id":"ca-ogl-lgo","data_series_name":{"fr":"","en":""},"relationships_as_subject":[],"license_title":"Open Government Licence - Canada","restrictions":"unrestricted","organization":{"description":"","created":"2016-09-23T17:26:17.294681","title":"Treasury Board of Canada Secretariat | Secrétariat du Conseil du Trésor du Canada","name":"tbs-sct","is_organization":true,"state":"active","image_url":"","revision_id":"189d1ca6-d57a-4277-a432-7fda17346ce4","type":"organization","id":"81765FCD-32B3-4708-A593-3AA00705E62B","approval_status":"approved"},"name":"33ee0fd0-2796-4f9d-aba7-50c351a56122","isopen":false,"url":"{u'fr': u'http://www.tbs-sct.gc.ca/psm-fpfm/pensions/publications/reports-rapports/pspp-rrfp/2014/rpspp-rrrfp-fra.asp#toc16', u'en': u'http://www.tbs-sct.gc.ca/psm-fpfm/pensions/publications/reports-rapports/pspp-rrfp/2014/rpspp-rrrfp-eng.asp#toc16'}","notes":"This statistical table illustrates the number of pensions that became payable to men and women (per calendar year), the total dollar amount of pensions paid and the average pension amount. All amounts include indexation.","owner_org":"81765FCD-32B3-4708-A593-3AA00705E62B","audience":[],"license_url":"http://open.canada.ca/en/open-government-licence-canada","program_page_url":{},"title":"Report on the Public Service Pension Plan – Statistical Table 2.1.","revision_id":"818b9c7b-9b4a-4053-8dd0-cf4283bf75a6"}