{"notes_translated":{"fr":"Cet ensemble de données affiche les zones géographiques au sein duquel l’habitat essentiel des espèces terrestres en péril inscrites à l’annexe 1 de la Loi sur les espèces en péril (LEP) se produit en Ontario. En vertu de la LEP, est « l’habitat nécessaire à la survie ou au rétablissement d'une espèce sauvage inscrite et qui est identifié comme l’habitat essentiel de l’espèce dans le programme de rétablissement ou du plan d’action pour l’espèce. » La région géographique dans lequel l’habitat essentiel peut se produire est représenté comme « carrés de quadrillage ». Elles sont grosses (1, 10, 50 ou 100 km2) carrés fondée sur une grille UTM normalisée ou grossiers du système national de référence cartographique (SNRC) balances (1:50, 1/250) qui servent d’un drapeau pour examiner les espèces associées » Document de rétablissement. Toutefois, ce ne sont pas tous de la région au sein de ces carrés de quadrillage est l’habitat essentiel. Pour définir ce qui constitue l’habitat essentiel d’une espèce particulière, il est essentiel que cette information géospatiale être considéré en conjonction avec les renseignements complémentaires fournis dans le document de rétablissement de l’espèce (programme de rétablissement ou du plan d’action). Les documents de rétablissement sont disponibles sur les espèces en péril (EP) Registre public de la LEP (http://www.registrelep.gc.ca). La récupération des documents contiennent des renseignements importants au sujet de l’interprétation de l’information géospatiale, plus particulièrement en ce qui concerne les caractéristiques biologiques et environnementaux (« attributs biophysiques ») que la définition de l’habitat essentiel d’une espèce. Chaque espèce » ensemble de données est disponible pour téléchargement dans le cadre de la collecte de l’habitat essentiel pour l’Ontario. La collection comprend deux « final » et « proposé » l’habitat essentiel qu’il est illustré dans les documents de rétablissement. « Proposé » l’habitat essentiel décrit dans les documents de rétablissement proposée n’a pas été officiellement identifié et est sujet à changement avant qu’il soit affiché comme définitif. Malgré l’utilisation du terme « final », il est important de noter que les documents de rétablissement (et, par conséquent, l’habitat essentiel) peut être modifié de temps à autre. Le registre public des espèces en péril est toujours considérée comme la principale source d’information pour l’habitat essentiel de l’information. Espèces sont ajoutés à la collection, car les données devient prêt, ce qui peut se produire après le document de rétablissement a été affiché sur le registre public des espèces en péril et peut être modifiée une fois que le document est affiché de rétablissement final ou est modifiée. L’identification de l’habitat essentiel n’est pas automatiquement une « protection ». Faisant partie ou non du gouvernement fédéral de lois ou de règlements administratifs peuvent être mises en place pour assurer la protection.","en":"This dataset displays the geographic areas within which critical habitat for terrestrial species at risk listed on Schedule 1 of the federal Species at Risk Act (SARA) occurs in Ontario. Under SARA, is “the habitat that is necessary for the survival or recovery of a listed wildlife species and that is identified as the species’ critical habitat in the recovery strategy or action plan for the species.”The geographic area within which critical habitat may occur is represented as “grid squares”. These are coarse (1, 10, 50 or 100 km2) squares based on a standardized UTM grid or coarse National Topographic System (NTS) scales (1:50, 1:250) that serve as a flag to review the associated species’ recovery document. However, not all of the area within these grid squares is critical habitat. To precisely define what constitutes critical habitat for a particular species, it is essential that this geospatial information be considered in conjunction with complementary information provided in the species’ recovery document (recovery strategy and/or action plan). Recovery documents are available from the Species at Risk (SAR) Public Registry (http://www.sararegistry.gc.ca). The recovery documents contain important information about the interpretation of the geospatial information, especially regarding the biological and environmental features (“biophysical attributes”) that complete the definition of a species’ critical habitat.Each species’ dataset is available for download as part of the collection of critical habitat for Ontario. The collection includes both “final” and “proposed” critical habitat as it is depicted in the recovery documents. “Proposed” critical habitat depicted in proposed recovery documents has not been formally identified and is subject to change before it is posted as final. Despite the use of the term “final”, it is important to note that recovery documents (and therefore critical habitat) may be amended from time to time. The SAR Public Registry is always considered as the main source for critical habitat information. Species are added to the collection as the data becomes ready, which may occur after the recovery document has been posted on the SAR Public Registry and may be modified once the recovery document is posted final or is amended. Critical habitat identification alone is not an automatic “protection” designation. Federal or non-federal laws or bylaws may be in place to provide protection."},"place_of_publication":[],"imso_approval":"true","maintainer":null,"creator":"Environment and Climate Change Canada","association_type":[],"org_section":{},"jurisdiction":"federal","private":false,"maintainer_email":"marieclaude.archambault@canada.ca","num_tags":0,"contributor":{},"frequency":"as_needed","distributor":"{\"fr\": {\"organization_name\": \"Gouvernement du Canada; Environnement et Changement climatique Canada\", \"administrative_area\": \"\", \"country\": \"Canada (le)\", \"electronic_mail_address\": \"ec.enviroinfo.ec@canada.ca\", \"address\": \"4905, rue Dufferin\"}, \"en\": {\"city\": \"Toronto\", \"administrative_area\": \"\", \"country\": \"Canada\", \"organization_name\": \"Government of Canada; Environment and Climate Change Canada\", \"postal_code\": \"M3H 5T4\", \"address\": \"4905 Dufferin Street\", \"electronic_mail_address\": \"ec.enviroinfo.ec@canada.ca\"}}","data_series_issue_identification":{},"ready_to_publish":"true","id":"455125da-453b-4f16-b731-c7625522283c","metadata_created":"2020-03-18T20:01:57.342584","subject":["nature_and_environment","science_and_technology"],"hierarchy_level":"series; série","spatial_representation_type":["vector"],"metadata_modified":"2020-04-08T16:58:44.743525","author":null,"author_email":null,"geographic_region":[],"position_name":{},"keywords":{"fr":["espèces en péril (EEP)","Habitat essentiel","Loi sur les espèces en péril (LEP)","LEP","grille UTM normalisée","Service canadien de la faune (SCF)","Ontario","Nature et biodiversité - habitat","Espèce","Protéger le bien-être des espèces","Élaborer des plans de rétablissement; de gestion et de conservation des espèces","Ontario (ON)","Diversité biologique"],"en":["Species at Risk (SAR)","Critical habitat","Species at Risk Act (SARA)","SARA","standardized UTM grid","Canadian Wildlife Service (CWS)","Ontario","Nature and Biodiversity - Habitat","Species","Protect Species Well-Being","Develop Species Recovery / Management / Conservation Plans","Ontario (ON)","Biological diversity"]},"contact_information":"{\"fr\": {\"administrative_area\": \"\", \"delivery_point\": \"4905, rue Dufferin\", \"electronic_mail_address\": \"marieclaude.archambault@canada.ca\", \"country\": \"Canada (le)\"}, \"en\": {\"city\": \"Toronto\", \"administrative_area\": \"\", \"country\": \"Canada\", \"postal_code\": \"M3H 5T4\", \"delivery_point\": \"4905 Dufferin Street\", \"electronic_mail_address\": \"marieclaude.archambault@canada.ca\"}}","parent_id":"f19114f1-9ff8-45a9-9440-a71ebb2d367a","state":"active","version":null,"relationships_as_object":[],"time_period_coverage_start":"2002-12-12 00:00:00","title_translated":{"fr":"Chardon de Hill (Cirsium hilli) - Habitat essentiel des espèces en péril - Ontario","en":"Hill's Thistle (Cirsium hilli) - Critical Habitat for Species at Risk - Ontario"},"type":"dataset","resources":[{"cache_last_updated":null,"package_id":"455125da-453b-4f16-b731-c7625522283c","datastore_active":false,"id":"7f0bcb0b-e792-43b8-9cf5-882fbef7e7f1","state":"active","name_translated":{"fr":"PCA_CH_807_Cirsium_hilli_Grid_1km_EN.kmz","en":"PCA_CH_807_Cirsium_hilli_Grid_1km_EN.kmz"},"hash":"","description":"","format":"KMZ","mimetype_inner":null,"url_type":null,"mimetype":null,"cache_url":null,"name":"PCA_CH_807_Cirsium_hilli_Grid_1km_EN.kmz","language":["en","fr"],"created":"2020-04-08T16:58:44.863235","url":"http://data.ec.gc.ca/data/species/developplans/critical-habitat-for-species-at-risk-ontario/hill-s-thistle-cirsium-hilli-critical-habitat-for-species-at-risk-ontario/PCA_CH_807_Cirsium_hilli_Grid_1km_EN.kmz","last_modified":null,"data_quality":[],"position":0,"revision_id":"2399d985-5ad1-45fd-8dc1-d62ec91a6af8","resource_type":"dataset"},{"cache_last_updated":null,"package_id":"455125da-453b-4f16-b731-c7625522283c","datastore_active":false,"id":"e85aa810-50d1-4e0a-b3b9-af43b0351565","state":"active","name_translated":{"fr":"PCA_CH_807_Cirsium_hilli_EN.kmz","en":"PCA_CH_807_Cirsium_hilli_EN.kmz"},"hash":"","description":"","format":"KMZ","mimetype_inner":null,"url_type":null,"mimetype":null,"cache_url":null,"name":"PCA_CH_807_Cirsium_hilli_EN.kmz","language":["en","fr"],"created":"2020-04-08T16:58:44.863247","url":"http://data.ec.gc.ca/data/species/developplans/critical-habitat-for-species-at-risk-ontario/hill-s-thistle-cirsium-hilli-critical-habitat-for-species-at-risk-ontario/PCA_CH_807_Cirsium_hilli_EN.kmz","last_modified":null,"data_quality":[],"position":1,"revision_id":"2399d985-5ad1-45fd-8dc1-d62ec91a6af8","resource_type":"dataset"},{"cache_last_updated":null,"package_id":"455125da-453b-4f16-b731-c7625522283c","datastore_active":false,"id":"89c03d62-3216-486f-9b9c-42c0bec079be","state":"active","name_translated":{"fr":"PCA_CH_807_Cirsium_hilli.gdb.zip","en":"PCA_CH_807_Cirsium_hilli.gdb.zip"},"hash":"","description":"","format":"ZIP","mimetype_inner":null,"url_type":null,"mimetype":null,"cache_url":null,"name":"PCA_CH_807_Cirsium_hilli.gdb.zip","language":["en","fr"],"created":"2020-04-08T16:58:44.863251","url":"http://data.ec.gc.ca/data/species/developplans/critical-habitat-for-species-at-risk-ontario/hill-s-thistle-cirsium-hilli-critical-habitat-for-species-at-risk-ontario/PCA_CH_807_Cirsium_hilli.gdb.zip","last_modified":null,"data_quality":[],"position":2,"revision_id":"2399d985-5ad1-45fd-8dc1-d62ec91a6af8","resource_type":"dataset"},{"cache_last_updated":null,"package_id":"455125da-453b-4f16-b731-c7625522283c","datastore_active":false,"id":"840e0ec6-9f83-4f93-bc41-995e1dbfe526","state":"active","name_translated":{"fr":"WMS","en":"WMS"},"hash":"","description":"","format":"WMS","mimetype_inner":null,"url_type":null,"mimetype":null,"cache_url":null,"name":"WMS","language":["en"],"created":"2020-04-08T16:58:44.863254","url":"https://maps-cartes.ec.gc.ca/arcgis/services/ON_CriticalHabitat_ON_HabitatEssentiel/MapServer/WMSServer?request=GetCapabilities&service=WMS&layers=3&legend_format=image/png&feature_info_type=text/html","last_modified":null,"data_quality":[],"position":3,"revision_id":"2399d985-5ad1-45fd-8dc1-d62ec91a6af8","resource_type":"web_service"},{"cache_last_updated":null,"package_id":"455125da-453b-4f16-b731-c7625522283c","datastore_active":false,"id":"3c42e68f-74e5-48e3-9b43-50850f503456","state":"active","name_translated":{"fr":"WMS","en":"WMS"},"hash":"","description":"","format":"WMS","mimetype_inner":null,"url_type":null,"mimetype":null,"cache_url":null,"name":"WMS","language":["fr"],"created":"2020-04-08T16:58:44.863256","url":"https://maps-cartes.ec.gc.ca/arcgis/services/ON_CriticalHabitat_ON_HabitatEssentiel/MapServer/WMSServer?request=GetCapabilities&service=WMS&layers=3&legend_format=image/png&feature_info_type=text/html","last_modified":null,"data_quality":[],"position":4,"revision_id":"2399d985-5ad1-45fd-8dc1-d62ec91a6af8","resource_type":"web_service"},{"cache_last_updated":null,"package_id":"455125da-453b-4f16-b731-c7625522283c","datastore_active":false,"id":"40e52e65-45e3-4be5-bbbc-79866b86571e","state":"active","name_translated":{"fr":"ON_CriticalHabitat_ON_HabitatEssentiel","en":"ON_CriticalHabitat_ON_HabitatEssentiel"},"hash":"","description":"","format":"ESRI REST","mimetype_inner":null,"url_type":null,"mimetype":null,"cache_url":null,"name":"ON_CriticalHabitat_ON_HabitatEssentiel","language":["en"],"created":"2020-04-08T16:58:44.863259","url":"https://maps-cartes.ec.gc.ca/arcgis/rest/services/ON_CriticalHabitat_ON_HabitatEssentiel/MapServer/0","last_modified":null,"data_quality":[],"position":5,"revision_id":"2399d985-5ad1-45fd-8dc1-d62ec91a6af8","resource_type":"web_service"},{"cache_last_updated":null,"package_id":"455125da-453b-4f16-b731-c7625522283c","datastore_active":false,"id":"72ec2a11-6e2a-4c94-9686-6a125dcb64bc","state":"active","name_translated":{"fr":"ON_CriticalHabitat_ON_HabitatEssentiel","en":"ON_CriticalHabitat_ON_HabitatEssentiel"},"hash":"","description":"","format":"ESRI REST","mimetype_inner":null,"url_type":null,"mimetype":null,"cache_url":null,"name":"ON_CriticalHabitat_ON_HabitatEssentiel","language":["fr"],"created":"2020-04-08T16:58:44.863262","url":"https://maps-cartes.ec.gc.ca/arcgis/rest/services/ON_CriticalHabitat_ON_HabitatEssentiel/MapServer/0","last_modified":null,"data_quality":[],"position":6,"revision_id":"2399d985-5ad1-45fd-8dc1-d62ec91a6af8","resource_type":"web_service"},{"cache_last_updated":null,"package_id":"455125da-453b-4f16-b731-c7625522283c","datastore_active":false,"id":"06a5108f-9242-49ca-8e94-887ba395b80e","state":"active","name_translated":{"fr":"Voir le Dépôt de données d'ECCC (Anglais)","en":"View ECCC Data Mart (English)"},"hash":"","description":"","format":"HTML","mimetype_inner":null,"url_type":null,"mimetype":null,"cache_url":null,"name":"View ECCC Data Mart (English)","language":["en"],"created":"2020-04-08T16:58:44.863264","url":"http://data.ec.gc.ca/data/species/developplans/critical-habitat-for-species-at-risk-ontario/hill-s-thistle-cirsium-hilli-critical-habitat-for-species-at-risk-ontario","last_modified":null,"data_quality":[],"position":7,"revision_id":"2399d985-5ad1-45fd-8dc1-d62ec91a6af8","resource_type":"web_service"},{"cache_last_updated":null,"package_id":"455125da-453b-4f16-b731-c7625522283c","datastore_active":false,"id":"20823594-b59e-41e9-9b71-4339735c4e40","state":"active","name_translated":{"fr":"Voir le Dépôt de données d'ECCC (Français)","en":"View ECCC Data Mart (French)"},"hash":"","description":"","format":"HTML","mimetype_inner":null,"url_type":null,"mimetype":null,"cache_url":null,"name":"View ECCC Data Mart (French)","language":["fr"],"created":"2020-04-08T16:58:44.863267","url":"http://data.ec.gc.ca/data/species/developplans/critical-habitat-for-species-at-risk-ontario/hill-s-thistle-cirsium-hilli-critical-habitat-for-species-at-risk-ontario?lang=fr","last_modified":null,"data_quality":[],"position":8,"revision_id":"2399d985-5ad1-45fd-8dc1-d62ec91a6af8","resource_type":"web_service"}],"status":"ongoing","metadata_contact":{"fr":"Gouvernement du Canada; Environnement et Changement climatique Canada,ec.enviroinfo.ec@canada.ca","en":"Government of Canada; Environment and Climate Change Canada,ec.enviroinfo.ec@canada.ca"},"num_resources":9,"topic_category":["biota"],"tags":[],"aggregate_identifier":"","responsible_role":"RI_409","spatial":"{\"type\": \"Polygon\", \"coordinates\": [[[-83.5123281402, 44.4731680932], [-79.895999356, 44.4731680932], [-79.895999356, 45.9012151054], [-83.5123281402, 45.9012151054], [-83.5123281402, 44.4731680932]]]}","collection":"fgp","org_title_at_publication":{"fr":"Environnement et Changement climatique Canada","en":"Environment and Climate Change Canada"},"date_published":"2018-01-19 00:00:00","display_flags":["fgp_viewer"],"file_id":"455125da-453b-4f16-b731-c7625522283c","groups":[],"creator_user_id":"b88b9549-3a4b-43a9-9375-5f3fc20fe782","data_series_name":{},"relationships_as_subject":[],"license_title":"Open Government Licence - Canada","restrictions":"unrestricted","organization":{"description":"","created":"2016-09-23T17:25:23.598825","title":"Environment and Climate Change Canada | Environnement et Changement climatique Canada","name":"ec","is_organization":true,"state":"active","image_url":"","revision_id":"38f75d48-68d0-46b4-9f5b-89618853cde4","type":"organization","id":"49E2ADF4-AD7A-43EB-85C8-6433D37ED62C","approval_status":"approved"},"name":"455125da-453b-4f16-b731-c7625522283c","isopen":false,"license_id":"ca-ogl-lgo","url":null,"notes":"This dataset displays the geographic areas within which critical habitat for terrestrial species at risk listed on Schedule 1 of the federal Species at Risk Act (SARA) occurs in Ontario. Under SARA, is “the habitat that is necessary for the survival or recovery of a listed wildlife species and that is identified as the species’ critical habitat in the recovery strategy or action plan for the species.”The geographic area within which critical habitat may occur is represented as “grid squares”. These are coarse (1, 10, 50 or 100 km2) squares based on a standardized UTM grid or coarse National Topographic System (NTS) scales (1:50, 1:250) that serve as a flag to review the associated species’ recovery document. However, not all of the area within these grid squares is critical habitat. To precisely define what constitutes critical habitat for a particular species, it is essential that this geospatial information be considered in conjunction with complementary information provided in the species’ recovery document (recovery strategy and/or action plan). Recovery documents are available from the Species at Risk (SAR) Public Registry (http://www.sararegistry.gc.ca). The recovery documents contain important information about the interpretation of the geospatial information, especially regarding the biological and environmental features (“biophysical attributes”) that complete the definition of a species’ critical habitat.Each species’ dataset is available for download as part of the collection of critical habitat for Ontario. The collection includes both “final” and “proposed” critical habitat as it is depicted in the recovery documents. “Proposed” critical habitat depicted in proposed recovery documents has not been formally identified and is subject to change before it is posted as final. Despite the use of the term “final”, it is important to note that recovery documents (and therefore critical habitat) may be amended from time to time. The SAR Public Registry is always considered as the main source for critical habitat information. Species are added to the collection as the data becomes ready, which may occur after the recovery document has been posted on the SAR Public Registry and may be modified once the recovery document is posted final or is amended. Critical habitat identification alone is not an automatic “protection” designation. Federal or non-federal laws or bylaws may be in place to provide protection.","owner_org":"49E2ADF4-AD7A-43EB-85C8-6433D37ED62C","audience":[],"license_url":"http://open.canada.ca/en/open-government-licence-canada","program_page_url":{},"title":"Hill's Thistle (Cirsium hilli) - Critical Habitat for Species at Risk - Ontario","revision_id":"75bbf310-7545-46c7-ad96-65d6bbf45bef"}