{"notes_translated":{"fr":"<p>  Pourcentage d’utilisateurs d’Internet selon certains services et technologies liés à Internet tels que l’accès à domicile, l’utilisation d’appareils intelligents pour la maison, l’utilisation de téléphones intelligents, l’utilisation de comptes de réseaux sociaux, l’utilisation ou l'achat de services de diffusion en continu, l’utilisation de services gouvernementaux en ligne et les achats en ligne.<br></p>","en":"<p>    Percentage of Internet users by selected Internet service and technology, such as; home Internet access, use of smart home devices, use of smartphones, use of social networking accounts, use or purchase of streaming services, use of government services online and online shopping.<br></p>"},"imso_approval":"true","maintainer":null,"association_type":[],"org_section":{},"jurisdiction":"federal","private":false,"maintainer_email":"statcan.infostats-infostats.statcan@canada.ca","num_tags":0,"contributor":{},"frequency":"as_needed","keywords":{"fr":["tableau","utilisation d'internet","utilisation d'internet par les particuliers et les ménages","économie et société numériques"],"en":["digital economy and society","individual and household internet use","internet use","table"]},"data_series_issue_identification":{"fr":"Tableau 22100113","en":"Table 22100113"},"ready_to_publish":"true","id":"75e0a4a2-2bb0-4727-af1f-ff9db913171d","metadata_created":"2019-10-29T12:45:35.143609","subject":["information_and_communications"],"spatial_representation_type":[],"metadata_modified":"2021-06-18T13:40:13.123924","author":null,"author_email":"statcan.infostats-infostats.statcan@canada.ca","geographic_region":[],"position_name":{},"state":"active","version":null,"relationships_as_object":[],"creator_user_id":"6b600515-c266-4584-a219-d084c980fd47","title_translated":{"fr":"Utilisation de services et de technologies liés à Internet, selon le groupe d’âge et le quartile de revenu du ménage","en":"Use of Internet services and technologies by age group and household income quartile"},"type":"dataset","resources":[{"cache_last_updated":null,"package_id":"75e0a4a2-2bb0-4727-af1f-ff9db913171d","datastore_active":false,"id":"deaa1f8c-aa0c-433c-8cea-af013a8c59c5","state":"active","name_translated":{"fr":"Ensembles de données","en":"Dataset"},"hash":"","description":"","format":"CSV","mimetype_inner":null,"url_type":null,"mimetype":null,"cache_url":null,"name":"Dataset","language":["fr"],"created":"2021-06-18T13:40:13.177745","url":"https://www150.statcan.gc.ca/n1/tbl/csv/22100113-fra.zip","last_modified":null,"data_quality":[],"position":0,"revision_id":"fd75c91e-e114-4701-bc12-e899856da4e0","resource_type":"dataset"},{"cache_last_updated":null,"package_id":"75e0a4a2-2bb0-4727-af1f-ff9db913171d","datastore_active":false,"id":"f7585c56-095d-44c5-b6f4-5293fbc0d462","state":"active","name_translated":{"fr":"Ensembles de données","en":"Dataset"},"hash":"","description":"","format":"CSV","mimetype_inner":null,"url_type":null,"mimetype":null,"cache_url":null,"name":"Dataset","language":["en"],"created":"2021-06-18T13:40:13.177766","url":"https://www150.statcan.gc.ca/n1/tbl/csv/22100113-eng.zip","last_modified":null,"data_quality":[],"position":1,"revision_id":"fd75c91e-e114-4701-bc12-e899856da4e0","resource_type":"dataset"},{"cache_last_updated":null,"package_id":"75e0a4a2-2bb0-4727-af1f-ff9db913171d","datastore_active":false,"id":"5209d43b-6e94-4836-95e6-93ec215bba45","state":"active","name_translated":{"fr":"Ensembles de données","en":"Dataset"},"hash":"","description":"","format":"XML","mimetype_inner":null,"url_type":null,"mimetype":null,"cache_url":null,"name":"Dataset","language":["en","fr"],"created":"2021-06-18T13:40:13.177769","url":"https://www150.statcan.gc.ca/n1/tbl/sdmx/22100113-SDMX.zip","last_modified":null,"data_quality":[],"position":2,"revision_id":"fd75c91e-e114-4701-bc12-e899856da4e0","resource_type":"dataset"},{"cache_last_updated":null,"package_id":"75e0a4a2-2bb0-4727-af1f-ff9db913171d","datastore_active":false,"id":"c760a545-cbb4-4806-8e2d-41e398ba8f93","state":"active","name_translated":{"fr":"Document connexe","en":"Supporting Document"},"hash":"","description":"","format":"HTML","mimetype_inner":null,"url_type":null,"mimetype":null,"cache_url":null,"name":"Supporting Document","language":["fr"],"created":"2021-06-18T13:40:13.177771","url":"https://www150.statcan.gc.ca/t1/tbl1/fr/tv.action?pid=2210011301","last_modified":null,"data_quality":[],"position":3,"revision_id":"fd75c91e-e114-4701-bc12-e899856da4e0","resource_type":"guide"},{"cache_last_updated":null,"package_id":"75e0a4a2-2bb0-4727-af1f-ff9db913171d","datastore_active":false,"id":"3180bad3-a875-41aa-9a09-a3c50347e650","state":"active","name_translated":{"fr":"Document connexe","en":"Supporting Document"},"hash":"","description":"","format":"HTML","mimetype_inner":null,"url_type":null,"mimetype":null,"cache_url":null,"name":"Supporting Document","language":["en"],"created":"2021-06-18T13:40:13.177773","url":"https://www150.statcan.gc.ca/t1/tbl1/en/tv.action?pid=2210011301","last_modified":null,"data_quality":[],"position":4,"revision_id":"fd75c91e-e114-4701-bc12-e899856da4e0","resource_type":"guide"}],"place_of_publication":[],"metadata_contact":{},"num_resources":5,"topic_category":[],"tags":[],"collection":"primary","org_title_at_publication":{"fr":"Statistique Canada","en":"Statistics Canada"},"date_published":"2019-10-29 08:30:00","display_flags":[],"groups":[],"license_id":"ca-ogl-lgo","data_series_name":{"fr":"Tableau","en":"Table"},"relationships_as_subject":[],"license_title":"Open Government Licence - Canada","restrictions":"unrestricted","organization":{"description":"","created":"2016-09-23T17:26:15.123077","title":"Statistics Canada | Statistique Canada","name":"statcan","is_organization":true,"state":"active","image_url":"","revision_id":"d6eb738d-1e03-4220-bdb8-35ee6754aba6","type":"organization","id":"A0F0FCFC-BC3B-4696-8B6D-E7E411D55BAC","approval_status":"approved"},"name":"75e0a4a2-2bb0-4727-af1f-ff9db913171d","isopen":false,"url":"{u'fr': u'http://www5.statcan.gc.ca/cansim/home-accueil?lang=fra', u'en': u'http://www5.statcan.gc.ca/cansim/home-accueil?lang=eng'}","notes":"<p>    Percentage of Internet users by selected Internet service and technology, such as; home Internet access, use of smart home devices, use of smartphones, use of social networking accounts, use or purchase of streaming services, use of government services online and online shopping.<br></p>","owner_org":"A0F0FCFC-BC3B-4696-8B6D-E7E411D55BAC","audience":[],"license_url":"http://open.canada.ca/en/open-government-licence-canada","program_page_url":{},"title":"Use of Internet services and technologies by age group and household income quartile","revision_id":"6fa011f0-b1ee-4c9a-851f-2491f6d7ee3b"}