{"notes_translated":{"fr":"Les donnees sur le denombrement des ecoles elementaires et secondaires financees par les fonds publics incluent : * l'annee scolaire * la region * le numero du conseil * le nom du conseil * la langue du conseil * le type du conseil * les ecoles elementaires * les ecoles secondaires * le nombre total d'ecoles Source : telles que mises et tenues a jour par les ecoles et les conseils scolaires dans le Systeme d'information scolaire de l'Ontario (SISOn) dans la presentation d'octobre.","en":"The number of publicly funded elementary and secondary schools. Data includes: * academic year * region * board number * board name * board language * board type * elementary schools * secondary schools * total schools Source: As updated/maintained by schools and school boards in the Ontario School Information System (OnSIS), October Submission."},"imso_approval":"true","maintainer":null,"creator":"Education","association_type":[],"org_section":{},"jurisdiction":"provincial","private":false,"maintainer_email":"opengov@ontario.ca","num_tags":0,"keywords":{"fr-t-en":["Éducation et formation"],"en":["Education and Training"]},"frequency":"P1Y","contributor":{},"data_series_issue_identification":{},"ready_to_publish":"true","id":"81c48bca-938c-413c-8c35-a33f96ed8660","metadata_created":"2021-01-27T16:12:00.166833","subject":["education_and_training"],"hierarchy_level":"dataset; jeuDonnées","spatial_representation_type":[],"metadata_modified":"2021-10-20T08:01:23.125915","author":null,"author_email":null,"geographic_region":[],"position_name":{"fr":"Education","en":"Education"},"contact_information":"{\"fr\": {\"organization_name\": \"Gouvernement de l'Ontario;Gouvernement de l'Ontario;Education\",\"electronic_mail_address\": \"opengov@ontario.ca\"},\"en\": {\"organization_name\": \"Government of Ontario;Government of Ontario;Education\",\"electronic_mail_address\": \"opengov@ontario.ca\"}}","state":"active","version":null,"relationships_as_object":[],"time_period_coverage_start":"2014-09-01 00:00:00","title_translated":{"fr":"Nombre d’écoles élémentaires et secondaires par conseil scolaire ou administration scolaire","en":"Number of elementary and secondary schools by school board/school authority"},"type":"dataset","resources":[{"cache_last_updated":null,"package_id":"81c48bca-938c-413c-8c35-a33f96ed8660","datastore_active":false,"id":"9da12a34-d079-4d8d-8d72-75d5cdf98097","state":"active","name_translated":{"fr-t-en":"Année académique 2014-2015","en":"2014-2015 Academic Year"},"hash":"","description":"","format":"XLSX","mimetype_inner":null,"url_type":null,"mimetype":null,"cache_url":null,"name":"2014-2015 Academic Year","language":["en"],"created":"2021-10-20T08:01:23.483605","url":"https://files.ontario.ca/opendata/number_of_schools_by_board_2014-2015_en.xlsx","last_modified":null,"data_quality":[],"position":0,"revision_id":"e0348424-0ab2-4cb0-852d-03ed296be2c4","resource_type":"dataset"},{"cache_last_updated":null,"package_id":"81c48bca-938c-413c-8c35-a33f96ed8660","datastore_active":false,"id":"9f24fa31-6503-4a2a-a0ac-792a50fff759","state":"active","name_translated":{"fr-t-en":"Année académique 2014-2015","en":"2014-2015 Academic Year"},"hash":"","description":"","format":"TXT","mimetype_inner":null,"url_type":null,"mimetype":null,"cache_url":null,"name":"2014-2015 Academic Year","language":["en"],"created":"2021-10-20T08:01:23.483614","url":"https://files.ontario.ca/opendata/number_of_schools_by_board_2014-2015_en.txt","last_modified":null,"data_quality":[],"position":1,"revision_id":"e0348424-0ab2-4cb0-852d-03ed296be2c4","resource_type":"dataset"},{"cache_last_updated":null,"package_id":"81c48bca-938c-413c-8c35-a33f96ed8660","datastore_active":false,"id":"eb00fff4-4538-43e1-b051-aa18a6e0e413","state":"active","name_translated":{"fr-t-en":"Année académique 2015-2016","en":"2015-2016 Academic Year"},"hash":"","description":"","format":"XLSX","mimetype_inner":null,"url_type":null,"mimetype":null,"cache_url":null,"name":"2015-2016 Academic Year","language":["en"],"created":"2021-10-20T08:01:23.483618","url":"https://files.ontario.ca/opendata/number_of_schools_by_board_2015_2016_en.xlsx","last_modified":null,"data_quality":[],"position":2,"revision_id":"e0348424-0ab2-4cb0-852d-03ed296be2c4","resource_type":"dataset"},{"cache_last_updated":null,"package_id":"81c48bca-938c-413c-8c35-a33f96ed8660","datastore_active":false,"id":"5b5e824c-1463-4e03-9454-63b2387cb4c1","state":"active","name_translated":{"fr-t-en":"Année académique 2015-2016","en":"2015-2016 Academic Year"},"hash":"","description":"","format":"TXT","mimetype_inner":null,"url_type":null,"mimetype":null,"cache_url":null,"name":"2015-2016 Academic Year","language":["en"],"created":"2021-10-20T08:01:23.483620","url":"https://files.ontario.ca/opendata/number_of_schools_by_board_2015-2016_en.txt","last_modified":null,"data_quality":[],"position":3,"revision_id":"e0348424-0ab2-4cb0-852d-03ed296be2c4","resource_type":"dataset"},{"cache_last_updated":null,"package_id":"81c48bca-938c-413c-8c35-a33f96ed8660","datastore_active":false,"id":"2950a106-550a-4318-ad72-b7f1b44fc134","state":"active","name_translated":{"fr-t-en":"Année académique 2016-2017","en":"2016-2017 Academic Year"},"hash":"","description":"","format":"TXT","mimetype_inner":null,"url_type":null,"mimetype":null,"cache_url":null,"name":"2016-2017 Academic Year","language":["en"],"created":"2021-10-20T08:01:23.483623","url":"https://files.ontario.ca/opendata/number_of_schools_by_board_2016-2017_en.txt","last_modified":null,"data_quality":[],"position":4,"revision_id":"e0348424-0ab2-4cb0-852d-03ed296be2c4","resource_type":"dataset"},{"cache_last_updated":null,"package_id":"81c48bca-938c-413c-8c35-a33f96ed8660","datastore_active":false,"id":"1b6252e4-fa19-4221-8f7a-8366832742e9","state":"active","name_translated":{"fr-t-en":"Année académique 2016-2017","en":"2016-2017 Academic Year"},"hash":"","description":"","format":"XLSX","mimetype_inner":null,"url_type":null,"mimetype":null,"cache_url":null,"name":"2016-2017 Academic Year","language":["en"],"created":"2021-10-20T08:01:23.483626","url":"https://files.ontario.ca/opendata/number_of_schools_by_board_2016_2017_en.xlsx","last_modified":null,"data_quality":[],"position":5,"revision_id":"e0348424-0ab2-4cb0-852d-03ed296be2c4","resource_type":"dataset"},{"cache_last_updated":null,"package_id":"81c48bca-938c-413c-8c35-a33f96ed8660","datastore_active":false,"id":"c731c771-af10-401a-a317-5193283b1811","state":"active","name_translated":{"fr-t-en":"Année académique 2017-2018","en":"2017-2018 Academic Year"},"hash":"","description":"","format":"XLSX","mimetype_inner":null,"url_type":null,"mimetype":null,"cache_url":null,"name":"2017-2018 Academic Year","language":["en"],"created":"2021-10-20T08:01:23.483628","url":"https://files.ontario.ca/opendata/number_of_schools_by_board_1718_en.xlsx","last_modified":null,"data_quality":[],"position":6,"revision_id":"e0348424-0ab2-4cb0-852d-03ed296be2c4","resource_type":"dataset"},{"cache_last_updated":null,"package_id":"81c48bca-938c-413c-8c35-a33f96ed8660","datastore_active":false,"id":"bc69cd50-7cc3-4399-83c0-1739392c9b31","state":"active","name_translated":{"fr-t-en":"Année académique 2017-2018","en":"2017-2018 Academic Year"},"hash":"","description":"","format":"TXT","mimetype_inner":null,"url_type":null,"mimetype":null,"cache_url":null,"name":"2017-2018 Academic Year","language":["en"],"created":"2021-10-20T08:01:23.483631","url":"https://files.ontario.ca/opendata/number_of_schools_by_board_1718_en.txt","last_modified":null,"data_quality":[],"position":7,"revision_id":"e0348424-0ab2-4cb0-852d-03ed296be2c4","resource_type":"dataset"},{"cache_last_updated":null,"package_id":"81c48bca-938c-413c-8c35-a33f96ed8660","datastore_active":false,"id":"9dd9e979-98d8-49ec-a053-2b7be5e981f3","state":"active","name_translated":{"fr-t-en":"Année académique 2018-2019","en":"2018-2019 Academic Year"},"hash":"","description":"","format":"XLSX","mimetype_inner":null,"url_type":null,"mimetype":null,"cache_url":null,"name":"2018-2019 Academic Year","language":["en"],"created":"2021-10-20T08:01:23.483633","url":"https://data.ontario.ca/dataset/81c48bca-938c-413c-8c35-a33f96ed8660/resource/08ad34d5-9e87-49ff-a255-0963f002e0f6/download/number__of_schools_by_board_1819_en.xlsx","last_modified":null,"data_quality":[],"position":8,"revision_id":"e0348424-0ab2-4cb0-852d-03ed296be2c4","resource_type":"dataset"},{"cache_last_updated":null,"package_id":"81c48bca-938c-413c-8c35-a33f96ed8660","datastore_active":false,"id":"c6248280-aea3-4d66-a3dc-52068be7841a","state":"active","name_translated":{"fr-t-en":"Année académique 2018-2019","en":"2018-2019 Academic Year"},"hash":"","description":"","format":"TXT","mimetype_inner":null,"url_type":null,"mimetype":null,"cache_url":null,"name":"2018-2019 Academic Year","language":["en"],"created":"2021-10-20T08:01:23.483636","url":"https://data.ontario.ca/dataset/81c48bca-938c-413c-8c35-a33f96ed8660/resource/bc6f1cfa-53c4-4d1a-b417-97be4d17f795/download/number_of_schools_by_board_1819_en.txt","last_modified":null,"data_quality":[],"position":9,"revision_id":"e0348424-0ab2-4cb0-852d-03ed296be2c4","resource_type":"dataset"},{"cache_last_updated":null,"package_id":"81c48bca-938c-413c-8c35-a33f96ed8660","datastore_active":false,"id":"d1f59365-b4c2-4887-a01a-bc79a49d00c7","state":"active","name_translated":{"fr-t-en":"Année académique 2019-2020","en":"2019-2020 Academic Year"},"hash":"","description":"","format":"XLSX","mimetype_inner":null,"url_type":null,"mimetype":null,"cache_url":null,"name":"2019-2020 Academic Year","language":["en"],"created":"2021-10-20T08:01:23.483639","url":"https://data.ontario.ca/dataset/81c48bca-938c-413c-8c35-a33f96ed8660/resource/840585fb-4293-448a-826d-529ed36c3607/download/number__of_schools_by_board_1920_en.xlsx","last_modified":null,"data_quality":[],"position":10,"revision_id":"e0348424-0ab2-4cb0-852d-03ed296be2c4","resource_type":"dataset"},{"cache_last_updated":null,"package_id":"81c48bca-938c-413c-8c35-a33f96ed8660","datastore_active":false,"id":"7e47c183-16ba-465e-9d9f-430635ee037b","state":"active","name_translated":{"fr-t-en":"Année académique 2019-2020","en":"2019-2020 Academic Year"},"hash":"","description":"","format":"TXT","mimetype_inner":null,"url_type":null,"mimetype":null,"cache_url":null,"name":"2019-2020 Academic Year","language":["en"],"created":"2021-10-20T08:01:23.483641","url":"https://data.ontario.ca/dataset/81c48bca-938c-413c-8c35-a33f96ed8660/resource/8ade579e-57e0-4f6f-954f-cda308dbc57d/download/number_of_schools_en.txt","last_modified":null,"data_quality":[],"position":11,"revision_id":"e0348424-0ab2-4cb0-852d-03ed296be2c4","resource_type":"dataset"},{"cache_last_updated":null,"package_id":"81c48bca-938c-413c-8c35-a33f96ed8660","datastore_active":false,"id":"10b699b5-01bd-44f7-9483-b8170df1b52c","state":"active","name_translated":{"fr-t-en":"Métadonnées d'origine (https://data.ontario.ca)","en":"Original metadata (https://data.ontario.ca)"},"hash":"","description":"","format":"HTML","mimetype_inner":null,"url_type":null,"mimetype":null,"cache_url":null,"name":"Original metadata (https://data.ontario.ca)","language":["en"],"created":"2021-10-20T08:01:23.483644","url":"https://data.ontario.ca/dataset/81c48bca-938c-413c-8c35-a33f96ed8660","last_modified":null,"data_quality":[],"position":12,"revision_id":"e0348424-0ab2-4cb0-852d-03ed296be2c4","resource_type":"website"},{"cache_last_updated":null,"package_id":"81c48bca-938c-413c-8c35-a33f96ed8660","datastore_active":false,"id":"f410dbac-7158-4fca-b9b8-7bf99bb05918","state":"active","name_translated":{"fr":"2015-2016 l’Année Scolaire","en-t-fr":"2015-2016 the School Year"},"hash":"","description":"","format":"XLSX","mimetype_inner":null,"url_type":null,"mimetype":null,"cache_url":null,"name":"2015-2016 the School Year","language":["fr"],"created":"2021-10-20T08:01:23.483647","url":"https://files.ontario.ca/opendata/number_of_schools_by_board_2015_2016_fr.xlsx","last_modified":null,"data_quality":[],"position":13,"revision_id":"e0348424-0ab2-4cb0-852d-03ed296be2c4","resource_type":"dataset"},{"cache_last_updated":null,"package_id":"81c48bca-938c-413c-8c35-a33f96ed8660","datastore_active":false,"id":"34718599-1794-4de7-b8c9-d27dbfc5e32b","state":"active","name_translated":{"fr":"2015-2016 l’Année Scolaire","en-t-fr":"2015-2016 the School Year"},"hash":"","description":"","format":"TXT","mimetype_inner":null,"url_type":null,"mimetype":null,"cache_url":null,"name":"2015-2016 the School Year","language":["fr"],"created":"2021-10-20T08:01:23.483649","url":"https://files.ontario.ca/opendata/number_of_schools_by_board_2015-2016_fr.txt","last_modified":null,"data_quality":[],"position":14,"revision_id":"e0348424-0ab2-4cb0-852d-03ed296be2c4","resource_type":"dataset"},{"cache_last_updated":null,"package_id":"81c48bca-938c-413c-8c35-a33f96ed8660","datastore_active":false,"id":"59b7ae6d-9995-459d-adb1-c7980e368334","state":"active","name_translated":{"fr":"2014-2015 l’Année Scolaire","en-t-fr":"2014-2015 the School Year"},"hash":"","description":"","format":"XLSX","mimetype_inner":null,"url_type":null,"mimetype":null,"cache_url":null,"name":"2014-2015 the School Year","language":["fr"],"created":"2021-10-20T08:01:23.483652","url":"https://files.ontario.ca/opendata/number_of_schools_by_board_2014-2015_fr.xlsx","last_modified":null,"data_quality":[],"position":15,"revision_id":"e0348424-0ab2-4cb0-852d-03ed296be2c4","resource_type":"dataset"},{"cache_last_updated":null,"package_id":"81c48bca-938c-413c-8c35-a33f96ed8660","datastore_active":false,"id":"db97a774-d5b6-4721-a27b-94290ad4a7cf","state":"active","name_translated":{"fr":"2014-2015 l’Année Scolaire","en-t-fr":"2014-2015 the School Year"},"hash":"","description":"","format":"TXT","mimetype_inner":null,"url_type":null,"mimetype":null,"cache_url":null,"name":"2014-2015 the School Year","language":["fr"],"created":"2021-10-20T08:01:23.483654","url":"https://files.ontario.ca/opendata/number_of_schools_by_board_2014-2015_fr.txt","last_modified":null,"data_quality":[],"position":16,"revision_id":"e0348424-0ab2-4cb0-852d-03ed296be2c4","resource_type":"dataset"},{"cache_last_updated":null,"package_id":"81c48bca-938c-413c-8c35-a33f96ed8660","datastore_active":false,"id":"904b6dad-5ba2-4bfc-8947-809461a72373","state":"active","name_translated":{"fr":"2016-2017 l’Année Scolaire","en-t-fr":"2016-2017 the School Year"},"hash":"","description":"","format":"XLSX","mimetype_inner":null,"url_type":null,"mimetype":null,"cache_url":null,"name":"2016-2017 the School Year","language":["fr"],"created":"2021-10-20T08:01:23.483657","url":"https://files.ontario.ca/opendata/number_of_schools_by_board_2016_2017_fr.xlsx","last_modified":null,"data_quality":[],"position":17,"revision_id":"e0348424-0ab2-4cb0-852d-03ed296be2c4","resource_type":"dataset"},{"cache_last_updated":null,"package_id":"81c48bca-938c-413c-8c35-a33f96ed8660","datastore_active":false,"id":"bf70ed61-40c9-42ce-9ead-7d6afeb6e113","state":"active","name_translated":{"fr":"2016-2017 l’Année Scolaire","en-t-fr":"2016-2017 the School Year"},"hash":"","description":"","format":"TXT","mimetype_inner":null,"url_type":null,"mimetype":null,"cache_url":null,"name":"2016-2017 the School Year","language":["fr"],"created":"2021-10-20T08:01:23.483660","url":"https://files.ontario.ca/opendata/number_of_schools_by_board_2016-2017_fr.txt","last_modified":null,"data_quality":[],"position":18,"revision_id":"e0348424-0ab2-4cb0-852d-03ed296be2c4","resource_type":"dataset"},{"cache_last_updated":null,"package_id":"81c48bca-938c-413c-8c35-a33f96ed8660","datastore_active":false,"id":"bba17133-49e9-495b-aa59-b828ef770ed1","state":"active","name_translated":{"fr":"2017-2018 l’Année Scolaire","en-t-fr":"2017-2018 the School Year"},"hash":"","description":"","format":"XLSX","mimetype_inner":null,"url_type":null,"mimetype":null,"cache_url":null,"name":"2017-2018 the School Year","language":["fr"],"created":"2021-10-20T08:01:23.483663","url":"https://files.ontario.ca/opendata/number_of_schools_by_board_1718_fr.xlsx","last_modified":null,"data_quality":[],"position":19,"revision_id":"e0348424-0ab2-4cb0-852d-03ed296be2c4","resource_type":"dataset"},{"cache_last_updated":null,"package_id":"81c48bca-938c-413c-8c35-a33f96ed8660","datastore_active":false,"id":"c1149b4c-681e-4196-820c-400ce4dd2b23","state":"active","name_translated":{"fr":"2017-2018 l’Année Scolaire","en-t-fr":"2017-2018 the School Year"},"hash":"","description":"","format":"TXT","mimetype_inner":null,"url_type":null,"mimetype":null,"cache_url":null,"name":"2017-2018 the School Year","language":["fr"],"created":"2021-10-20T08:01:23.483665","url":"https://files.ontario.ca/opendata/number_of_schools_by_board_1718_fr.txt","last_modified":null,"data_quality":[],"position":20,"revision_id":"e0348424-0ab2-4cb0-852d-03ed296be2c4","resource_type":"dataset"},{"cache_last_updated":null,"package_id":"81c48bca-938c-413c-8c35-a33f96ed8660","datastore_active":false,"id":"07f54b67-f4ad-4442-9b6b-a8c00213254e","state":"active","name_translated":{"fr":"2018-2019 l’Année Scolaire","en-t-fr":"2018-2019 the School Year"},"hash":"","description":"","format":"XLSX","mimetype_inner":null,"url_type":null,"mimetype":null,"cache_url":null,"name":"2018-2019 the School Year","language":["fr"],"created":"2021-10-20T08:01:23.483668","url":"https://data.ontario.ca/dataset/81c48bca-938c-413c-8c35-a33f96ed8660/resource/7da110ee-8a2e-45b6-b6c2-cb53a59a5295/download/number__of_schools_by_board_1819_fr.xlsx","last_modified":null,"data_quality":[],"position":21,"revision_id":"e0348424-0ab2-4cb0-852d-03ed296be2c4","resource_type":"dataset"},{"cache_last_updated":null,"package_id":"81c48bca-938c-413c-8c35-a33f96ed8660","datastore_active":false,"id":"78bbfe3a-e5fd-4f68-a8b8-2824f26ce4a5","state":"active","name_translated":{"fr":"2018-2019 l’Année Scolaire","en-t-fr":"2018-2019 the School Year"},"hash":"","description":"","format":"TXT","mimetype_inner":null,"url_type":null,"mimetype":null,"cache_url":null,"name":"2018-2019 the School Year","language":["fr"],"created":"2021-10-20T08:01:23.483670","url":"https://data.ontario.ca/dataset/81c48bca-938c-413c-8c35-a33f96ed8660/resource/5857aaeb-49b5-48c8-97dc-93b37d14e03b/download/number_of_schools_by_board_1819_fr.txt","last_modified":null,"data_quality":[],"position":22,"revision_id":"e0348424-0ab2-4cb0-852d-03ed296be2c4","resource_type":"dataset"},{"cache_last_updated":null,"package_id":"81c48bca-938c-413c-8c35-a33f96ed8660","datastore_active":false,"id":"58071e03-b670-47a8-8661-7c28eacffb00","state":"active","name_translated":{"fr":"2019-2020 l’Année Scolaire","en-t-fr":"2019-2020 the School Year"},"hash":"","description":"","format":"XLSX","mimetype_inner":null,"url_type":null,"mimetype":null,"cache_url":null,"name":"2019-2020 the School Year","language":["fr"],"created":"2021-10-20T08:01:23.483673","url":"https://data.ontario.ca/dataset/81c48bca-938c-413c-8c35-a33f96ed8660/resource/f5b26f96-c67a-41f2-98ab-6abeae31bd86/download/number__of_schools_by_board_1920_fr.xlsx","last_modified":null,"data_quality":[],"position":23,"revision_id":"e0348424-0ab2-4cb0-852d-03ed296be2c4","resource_type":"dataset"},{"cache_last_updated":null,"package_id":"81c48bca-938c-413c-8c35-a33f96ed8660","datastore_active":false,"id":"62da7bca-1efd-4e87-965d-5d380a374ca4","state":"active","name_translated":{"fr":"2019-2020 l’Année Scolaire","en-t-fr":"2019-2020 the School Year"},"hash":"","description":"","format":"TXT","mimetype_inner":null,"url_type":null,"mimetype":null,"cache_url":null,"name":"2019-2020 the School Year","language":["fr"],"created":"2021-10-20T08:01:23.483676","url":"https://data.ontario.ca/dataset/81c48bca-938c-413c-8c35-a33f96ed8660/resource/926aaa70-8e48-46ba-bea0-f216d6674db1/download/number_of_schools_fr.txt","last_modified":null,"data_quality":[],"position":24,"revision_id":"e0348424-0ab2-4cb0-852d-03ed296be2c4","resource_type":"dataset"}],"place_of_publication":[],"metadata_contact":{"fr":"Gouvernement de l'Ontario;Gouvernement de l'Ontario;Education","en":"Government of Ontario;Government of Ontario;Education"},"num_resources":25,"topic_category":["society"],"tags":[],"aggregate_identifier":"","responsible_role":"RI_414","restrictions":"unrestricted","collection":"federated","org_title_at_publication":{"fr":"Gouvernement de l'Ontario","en":"Government of Ontario"},"date_published":"2020-01-11 00:00:00","display_flags":[],"file_id":"81c48bca-938c-413c-8c35-a33f96ed8660","groups":[],"creator_user_id":"b88b9549-3a4b-43a9-9375-5f3fc20fe782","data_series_name":{},"relationships_as_subject":[],"license_title":"Open Government Licence – Ontario","time_period_coverage_end":"2020-08-31 00:00:00","federated_date_modified":"2021-10-18","organization":{"description":"","created":"2019-09-13T19:52:36.877501","title":"Government of Ontario | Gouvernement de l'Ontario","name":"on","is_organization":true,"state":"active","image_url":"","revision_id":"e7a0a625-eb50-433f-8534-d8619458354d","type":"organization","id":"dbbc4d72-a589-4ee5-bb0b-8de78ff8df65","approval_status":"approved"},"name":"81c48bca-938c-413c-8c35-a33f96ed8660","isopen":false,"license_id":"on-oglo","url":null,"notes":"The number of publicly funded elementary and secondary schools. Data includes: * academic year * region * board number * board name * board language * board type * elementary schools * secondary schools * total schools Source: As updated/maintained by schools and school boards in the Ontario School Information System (OnSIS), October Submission.","owner_org":"dbbc4d72-a589-4ee5-bb0b-8de78ff8df65","audience":[],"license_url":"https://www.ontario.ca/page/open-government-licence-ontario","program_page_url":{},"title":"Number of elementary and secondary schools by school board/school authority","revision_id":"f90a08fb-e0f5-4720-8688-4e3a13af49dc"}