{"notes_translated":{"fr":"Le programme Surveillance de l’influenza, qui est le système national de surveillance de l’activité grippale au Canada, suit de près, sur une base continue, la propagation de la grippe et des syndromes grippaux.\r\n\r\nLe programme Surveillance de l’influenza est un réseau regroupant des laboratoires, des hôpitaux, des cabinets de médecin et les ministères provinciaux et territoriaux de la Santé. Les objectifs du programme sont les suivants :\r\n•\tDÉTECTER : Reconnaître les signes permettant de détecter des épidémies et d’autres événements préoccupants pour la santé publique, d’en évaluer l’ampleur et d’intervenir.\r\n•\tINFORMER : Contribuer à la base de données probantes nécessaires à la planification, à l’élaboration et à la mise en œuvre de programmes et de politiques de santé axés sur la lutte contre la grippe.\r\n•\tDONNER LES MOYENS D’AGIR : Soutenir l’infrastructure de surveillance de la grippe à l’échelle nationale, y compris les collaborations nationales et internationales en matière de surveillance des pandémies et d’intervention en cas de pandémie.\r\n\r\nApprenez-en davantage sur le programme de Surveillance de l’influenza (link to https://www.canada.ca/fr/sante-publique/services/maladies/grippe-influenza/surveillance-influenza/propos-surveillance-influenza.html)\r\n","en":"FluWatch is Canada's national surveillance system that monitors the spread of influenza and influenza-like illnesses on an ongoing basis.\r\n\r\nThe FluWatch program consists of a network of labs, hospitals, doctor's offices and provincial and territorial ministries of health. Program objectives are:\r\n•\tDETECT: Identify signals to detect, assess and respond to epidemics and other events of public health concern.\r\n•\tINFORM: Contribute to the evidence base necessary to plan, develop and implement health programs and policies for the control of influenza.\r\n•\tENABLE: Support national infrastructure for influenza surveillance, including national and international collaborations related to surveillance and pandemic response.\r\n\r\nLearn more about the FluWatch influenza surveillance program. (link to https://www.canada.ca/en/public-health/services/diseases/flu-influenza/influenza-surveillance/about-fluwatch.html) \r\n"},"imso_approval":"true","maintainer":null,"creator":"","association_type":[],"org_section":{"fr":"","en":""},"jurisdiction":"federal","private":false,"maintainer_email":"open-ouvert@tbs-sct.gc.ca","num_tags":0,"contributor":{"fr":"","en":""},"frequency":"P1Y","keywords":{"fr":["grippe","épidémiologe","virus respiratoire","surveillance de l'influenza"],"en":["influenza","epidmiology","respiratory virus","FluWatch"]},"data_series_issue_identification":{"fr":"","en":""},"ready_to_publish":"true","id":"d1046c8f-0480-44f4-9c1f-0ca13f65362e","metadata_created":"2018-11-21T18:23:57.055877","subject":["health_and_safety"],"spatial_representation_type":[],"metadata_modified":"2018-11-21T18:23:57.055884","author":null,"author_email":null,"geographic_region":[],"position_name":{},"portal_release_date":"2018-11-21","digital_object_identifier":"","state":"active","version":null,"relationships_as_object":[],"creator_user_id":"4cfa9a9c-1d95-40eb-86f9-bc0c8ec45d1f","title_translated":{"fr":"Surveillance de l'influenza 2015-2016 ","en":"FluWatch 2015-2016"},"type":"dataset","resources":[{"cache_last_updated":null,"unique_identifier":"","package_id":"d1046c8f-0480-44f4-9c1f-0ca13f65362e","datastore_active":false,"id":"3665668c-bd6b-42bd-9f9c-8f5dc17f5bdc","character_set":"","state":"active","name_translated":{"fr":"Détections/Isolements de virus respiratoires  ","en":"Respiratory Virus Detections/Isolations"},"hash":"","description":"","format":"CSV","date_published":"","mimetype_inner":null,"url_type":null,"mimetype":null,"cache_url":null,"name":"Respiratory Virus Detections/Isolations","language":["en"],"created":"2018-11-21T18:23:58.518698","url":"http://health.canada.ca/apps/open-data/fluwatch/FluWatch2015-2016RespiratoryVirusDetectionsIsolations-en.csv","last_modified":null,"resource_type":"dataset","position":0,"revision_id":"63b7ec21-4d21-4abc-bad3-5eaf5d71a83f","data_quality":[]},{"cache_last_updated":null,"unique_identifier":"","package_id":"d1046c8f-0480-44f4-9c1f-0ca13f65362e","datastore_active":false,"id":"62ba5484-79ce-4ed4-a19f-d4c583d0b253","character_set":"","state":"active","name_translated":{"fr":"Détections/Isolements de virus respiratoires  ","en":"Respiratory Virus Detections/Isolations"},"hash":"","description":"","format":"CSV","date_published":"","mimetype_inner":null,"url_type":null,"mimetype":null,"cache_url":null,"name":"Respiratory Virus Detections/Isolations","language":["fr"],"created":"2018-11-21T18:23:58.518706","url":"http://health.canada.ca/apps/open-data/fluwatch/FluWatch2015-2016RespiratoryVirusDetectionsIsolations-fr.csv","last_modified":null,"resource_type":"dataset","position":1,"revision_id":"63b7ec21-4d21-4abc-bad3-5eaf5d71a83f","data_quality":[]},{"cache_last_updated":null,"unique_identifier":"","package_id":"d1046c8f-0480-44f4-9c1f-0ca13f65362e","datastore_active":false,"id":"46f57f8e-ca80-4e2e-9434-0b9dd8dfb1d9","character_set":"","state":"active","name_translated":{"fr":"Détections/Isolements de virus respiratoires  - Dictionnaire de données","en":"Respiratory Virus Detections/Isolations – Data Dictionary"},"hash":"","description":"","format":"RTF","date_published":"","mimetype_inner":null,"url_type":null,"mimetype":null,"cache_url":null,"name":"Respiratory Virus Detections/Isolations – Data Dictionary","language":["en"],"created":"2018-11-21T18:23:58.518709","url":"http://health.canada.ca/apps/open-data/fluwatch/data-dictionary-dictionnaire-donnees-en.rtf","last_modified":null,"resource_type":"terminology","position":2,"revision_id":"63b7ec21-4d21-4abc-bad3-5eaf5d71a83f","data_quality":[]},{"cache_last_updated":null,"unique_identifier":"","package_id":"d1046c8f-0480-44f4-9c1f-0ca13f65362e","datastore_active":false,"id":"6f980916-ea63-4b77-b898-a7897d803a65","character_set":"","state":"active","name_translated":{"fr":"Détections/Isolements de virus respiratoires  - Dictionnaire de données","en":"Respiratory Virus Detections/Isolations – Data Dictionary"},"hash":"","description":"","format":"RTF","date_published":"","mimetype_inner":null,"url_type":null,"mimetype":null,"cache_url":null,"name":"Respiratory Virus Detections/Isolations – Data Dictionary","language":["fr"],"created":"2018-11-21T18:23:58.518711","url":"http://health.canada.ca/apps/open-data/fluwatch/data-dictionary-dictionnaire-donnees-fr.rtf","last_modified":null,"resource_type":"terminology","position":3,"revision_id":"63b7ec21-4d21-4abc-bad3-5eaf5d71a83f","data_quality":[]},{"cache_last_updated":null,"unique_identifier":"","package_id":"d1046c8f-0480-44f4-9c1f-0ca13f65362e","datastore_active":false,"id":"f1993485-89b7-4da5-8c3c-cb1a45407d22","character_set":"","state":"active","name_translated":{"fr":"Détections/Isolements de virus respiratoires  - Dictionnaire de données","en":"Respiratory Virus Detections/Isolations – Data Dictionary"},"hash":"","description":"","format":"TXT","date_published":"","mimetype_inner":null,"url_type":null,"mimetype":null,"cache_url":null,"name":"Respiratory Virus Detections/Isolations – Data Dictionary","language":["en"],"created":"2018-11-21T18:23:58.518714","url":"http://health.canada.ca/apps/open-data/fluwatch/data-dictionary-dictionnaire-donnees-en.txt","last_modified":null,"resource_type":"terminology","position":4,"revision_id":"63b7ec21-4d21-4abc-bad3-5eaf5d71a83f","data_quality":[]},{"cache_last_updated":null,"unique_identifier":"","package_id":"d1046c8f-0480-44f4-9c1f-0ca13f65362e","datastore_active":false,"id":"c50bade7-0f5c-4644-a78d-64ddeb8a641a","character_set":"","state":"active","name_translated":{"fr":"Détections/Isolements de virus respiratoires  - Dictionnaire de données","en":"Respiratory Virus Detections/Isolations – Data Dictionary"},"hash":"","description":"","format":"TXT","date_published":"","mimetype_inner":null,"url_type":null,"mimetype":null,"cache_url":null,"name":"Respiratory Virus Detections/Isolations – Data Dictionary","language":["fr"],"created":"2018-11-21T18:23:58.518716","url":"http://health.canada.ca/apps/open-data/fluwatch/data-dictionary-dictionnaire-donnees-fr.txt","last_modified":null,"resource_type":"terminology","position":5,"revision_id":"63b7ec21-4d21-4abc-bad3-5eaf5d71a83f","data_quality":[]}],"place_of_publication":[],"metadata_contact":{},"num_resources":6,"topic_category":[],"tags":[],"spatial":"","collection":"primary","org_title_at_publication":{"fr":"Agence de la santé publique du Canada","en":"Public Health Agency of Canada"},"date_published":"2018-10-30 00:00:00","display_flags":[],"groups":[],"license_id":"ca-ogl-lgo","data_series_name":{"fr":"","en":""},"relationships_as_subject":[],"license_title":"Open Government Licence - Canada","restrictions":"unrestricted","organization":{"description":"","created":"2016-09-23T17:25:57.068700","title":"Public Health Agency of Canada | Agence de la santé publique du Canada","name":"phac-aspc","is_organization":true,"state":"active","image_url":"","revision_id":"96161da6-edc7-4d1d-99e0-baac9df7b3b9","type":"organization","id":"1C71053B-AA64-4646-956B-41631C396018","approval_status":"approved"},"name":"d1046c8f-0480-44f4-9c1f-0ca13f65362e","isopen":false,"url":null,"notes":"FluWatch is Canada's national surveillance system that monitors the spread of influenza and influenza-like illnesses on an ongoing basis.\r\n\r\nThe FluWatch program consists of a network of labs, hospitals, doctor's offices and provincial and territorial ministries of health. Program objectives are:\r\n•\tDETECT: Identify signals to detect, assess and respond to epidemics and other events of public health concern.\r\n•\tINFORM: Contribute to the evidence base necessary to plan, develop and implement health programs and policies for the control of influenza.\r\n•\tENABLE: Support national infrastructure for influenza surveillance, including national and international collaborations related to surveillance and pandemic response.\r\n\r\nLearn more about the FluWatch influenza surveillance program. (link to https://www.canada.ca/en/public-health/services/diseases/flu-influenza/influenza-surveillance/about-fluwatch.html) \r\n","owner_org":"1C71053B-AA64-4646-956B-41631C396018","audience":[],"license_url":"http://open.canada.ca/en/open-government-licence-canada","program_page_url":{"fr":"","en":""},"title":"FluWatch 2015-2016","revision_id":"63b7ec21-4d21-4abc-bad3-5eaf5d71a83f"}